Workbook
Name Slicer_Match_Confidence: #N/A
Name Slicer_Month: #N/A
Name Slicer_Standardized_Item: #N/A

Sheet Read Me
A2: Food Price Trends & Inflation
A3: Selected Food Prices — Nigeria, November 2024 to April 2025
A4: Prepared from the Selected Food Price Watch dataset, standardized across a Jan-2025 item-list change.
A5: 1. National Price Trend
A6: Summing the 33 items tracked continuously across all six months, the total basket rose from ₦84,423 in November 2024 to ₦95,788 in April 2025 — a 13.5% increase over five months, roughly 2.5% per month compounded.
A7: The rise wasn't a straight line. Prices climbed steadily through March, then eased slightly in April (₦97,158 → ₦95,788) — the only month-over-month dip in the entire window.
A8: Month | B8: Basket Total (₦)
A9: 45597 | B9: 84423
A10: 45627 | B10: 85881
A11: 45658 | B11: 89710
A12: 45689 | B12: 91022
A13: 45717 | B13: 97158
A14: 45748 | B14: 95788
A16: 2. Inflation Is Not Evenly Spread Across Food Groups
A17: Average year-on-year (YoY) inflation varies sharply by category as of April 2025:
A18: Category | B18: Avg YoY %
A19: Staples (rice, beans, garri, yam, plantain) | B19: 0.997
A20: Fish / seafood | B20: 0.875
A21: Processed / dairy | B21: 0.744
A22: Meat / poultry / eggs | B22: 0.738
A23: Cooking oils | B23: 0.719
A24: Vegetables / fruit | B24: 0.621
A26: Staples effectively doubled year-on-year. This is the most consequential finding in the dataset. Staples form the base of most Nigerian households' calorie intake and are the least substitutable food group, so this is where inflation is felt hardest — particularly by low-income households.
A27: 3. A Small Set of Items Is Driving Volatility
A28: Local Rice (Broken), Beans (Brown & White), Plantain, and Yam Tuber lead YoY inflation at 114–158%, all staples, consistent with the finding above.
A29: Separately, Onions and Agric Hen Eggs (crate of 30) are the most volatile items month-to-month (standard deviation of MoM change of roughly 27% and 17% respectively). These swing sharply rather than trending steadily — a supply-chain and perishability signature rather than a structural inflation one.
A30: 4. Geography Matters More Than Expected
A31: The average gap between a food's highest-priced state and its lowest-priced state is 123% — the median gap is exactly 100%, meaning for a typical item in a typical month, the price simply doubles between the cheapest and most expensive state.
A32: Item | B32: Avg State Price Gap
A33: Onions, fresh | B33: 3.02
A34: Agric Hen Eggs (crate of 30) | B34: 2.67
A35: Sweet potatoes | B35: 2.59
A36: Mudfish, dried | B36: 2.47
A37: Tomatoes, fresh | B37: 2.09
A39: Northeastern states (Yobe, Borno, Adamawa, Taraba, Gombe, Bauchi) appear as the lowest-price state 91 times across the dataset, versus only 34 times as the highest-price state. This is consistent with these being production zones where the crop is grown, but transport and insecurity constraints limit onward distribution — the price gap reflects logistics friction more than production cost.
A40: 5. Recommendations
A41: On the April price dip
A42: Treat the April easing with caution in any report. One month is not a trend reversal, and it follows five consecutive months of increases. It should be described as “stabilizing” rather than “improving” until May/June data confirms the direction.
A43: On food security framing
A44: The staples finding, not the volatile perishables, is the headline. A roughly 100% YoY increase in rice, beans, and yam affects nutrition security more than a volatile onion price, because households can skip onions for a week but not staples. Any policy-facing summary of this data should lead with the staples figure.
A45: On the state price gap
A46: This reads as a logistics and storage problem rather than a scarcity one. Northeastern states are cheap sources but rarely the expensive destination, meaning value is being lost — or captured elsewhere — between farm-gate and market. A useful follow-up would be to check whether transport-cost or post-harvest-loss data exists for the northeastern corridor to confirm the mechanism, particularly using field-level data collection tools such as ODK or KoboCollect.
A47: On using this dataset going forward
A48: Ten items were discontinued and nine new items were introduced starting January 2025, so any YoY comparison beyond January 2025 is only fully reliable for the 27 items confirmed as continuous series. Any external-facing use of this data should footnote that MoM/YoY figures for the remaining items may partly reflect a unit or brand change rather than pure price movement.
A50: Source: Selected Food Price Watch, standardized dataset, Nov 2024–Apr 2025.

Sheet Dashboard
A2: Pick an item below to update the price trend and inflation charts. Scroll down for national inflation and state comparisons.

Sheet PIVOT_TABLE
F2: Price Trend by item | O2: MOM/YOY BY ITEMS
A3: Average Price | B3: Column Labels | M3: Column Labels
A4: Row Labels | B4: Apr-2025 | C4: Dec-2024 | D4: Feb-2025 | E4: Jan-2025 | F4: Mar-2025 | G4: Nov-2024 | H4: Grand Total | M4: Apr-2025 | O4: Dec-2024 | Q4: Feb-2025 | S4: Jan-2025 | U4: Mar-2025 | W4: Nov-2024 | Y4: Total Sum of MoM | Z4: Total Sum of YoY
A5: Agric hen eggs | B5: 259.31615 | C5: 252.1655 | D5: 251.94052 | E5: 248.04139 | F5: 261.18235 | G5: 247.2591 | H5: 1519.905 | L5: Row Labels | M5: Sum of MoM | N5: Sum of YoY | O5: Sum of MoM | P5: Sum of YoY | Q5: Sum of MoM | R5: Sum of YoY | S5: Sum of MoM | T5: Sum of YoY | U5: Sum of MoM | V5: Sum of YoY | W5: Sum of MoM | X5: Sum of YoY
A6: Agric hen eggs, (a Crate of 30 pieces) | B6: 6150.1781 | C6: 2866.9151 | D6: 5976.1159 | E6: 5878.1406 | F6: 7670.5592 | G6: 2833.973 | H6: 31375.882 | L6: Agric hen eggs | M6: -0.7145176 | N6: 71.904558 | O6: 1.9843144 | P6: 129.14896 | Q6: 1.5719659 | R6: 80.887516 | S6: -1.6354765 | T6: 113.07567 | U6: 3.6682586 | V6: 76.566018 | W6: 4.9159544 | X6: 124.57914 | Y6: 9.7904993 | Z6: 596.16186
A7: Beans Brown | B7: 2429.3886 | C7: 2501.3235 | D7: 2465.9628 | E7: 2458.5333 | F7: 2616.2636 | G7: 2720.9608 | H7: 15192.433 | L7: Agric hen eggs, (a Crate of 30 pieces) | M7: -19.820995 | O7: 1.162399 | P7: 128.45794 | Q7: 1.666772 | U7: 28.353589 | W7: 6.0776605 | X7: 135.7368 | Y7: 17.439426 | Z7: 264.19474
A8: Beans white | B8: 2097.3099 | C8: 2319.0422 | D8: 2114.3292 | E8: 2123.853 | F8: 2215.1071 | G8: 2546.7025 | H8: 13416.344 | L8: Beans Brown | M8: -7.1428215 | N8: 75.040225 | O8: -8.0720499 | P8: 187.28788 | Q8: 0.30219169 | R8: 109.34789 | S8: -1.7107038 | T8: 151.74825 | U8: 6.0950166 | V8: 111.9458 | W8: -2.7706082 | X8: 224.36831 | Y8: -13.298975 | Z8: 859.73836
A9: Beef Bone in | C9: 5153.1849 | G9: 5073.7358 | H9: 10226.921 | L9: Beans white | M9: -5.3178976 | N9: 59.675942 | O9: -8.9394163 | P9: 179.44916 | Q9: -0.44841891 | R9: 82.770467 | S9: -8.4168028 | T9: 130.50827 | U9: 4.7664205 | V9: 85.79749 | W9: -2.1747433 | X9: 218.14424 | Y9: -20.530858 | Z9: 756.34557
A10: Beef Boneless | B10: 6544.5369 | C10: 6150.1829 | D10: 6269.4588 | E10: 6122.5683 | F10: 6523.501 | G10: 6001.3163 | H10: 37611.564 | L10: Beef Bone in | O10: 1.5658889 | P10: 91.079587 | W10: 3.237562 | X10: 92.916594 | Y10: 4.8034509 | Z10: 183.99618
A11: Bread (sliced), 450g | B11: 1688.3998 | C11: 1610.8262 | D11: 1633.1854 | E11: 1604.7842 | F11: 1680.1747 | G11: 1588.0267 | H11: 9805.397 | L11: Beef Boneless | M11: 0.32246286 | N11: 38.901257 | O11: 2.4805654 | P11: 95.433786 | Q11: 2.3991652 | R11: 71.551615 | S11: -0.44900434 | T11: 84.649351 | U11: 4.052059 | V11: 51.386684 | W11: 2.4364204 | X11: 98.09587 | Y11: 11.241669 | Z11: 440.01856
A12: Bread (unsliced), 450g | B12: 1547.5179 | C12: 1512.1275 | D12: 1497.4272 | E12: 1452.983 | F12: 1561.2438 | G12: 1486.2466 | H12: 9057.546 | L12: Bread (sliced), 450g | M12: 0.48954126 | O12: 1.4357127 | P12: 88.390264 | Q12: 1.7697791 | U12: 2.8771572 | W12: 2.4372917 | X12: 94.962032 | Y12: 9.009482 | Z12: 183.3523
A13: Carrots, fresh | B13: 1931.3179 | D13: 1838.5928 | E13: 1787.1615 | F13: 1947.0497 | H13: 7504.1219 | L13: Bread (unsliced), 450g | M13: -0.87916515 | O13: 1.7413605 | P13: 85.512238 | Q13: 3.0588232 | U13: 4.2617539 | W13: 2.1871298 | X13: 86.754307 | Y13: 10.369902 | Z13: 172.26654
A14: Cat fresh fish | B14: 5572.4934 | C14: 4347.4446 | D14: 5284.3595 | E14: 5226.8706 | F14: 5507.1099 | G14: 4259.987 | H14: 30198.265 | L14: Carrots, fresh | M14: -0.80798556 | Q14: 2.8778248 | U14: 5.8989086 | Y14: 7.9687479
A15: Catfish :dried | C15: 6044.0788 | G15: 5787.7445 | H15: 11831.823 | L15: Cat fresh fish | M15: 1.1872558 | N15: 77.437818 | O15: 2.0530016 | P15: 85.20189 | Q15: 1.0998735 | R15: 91.574837 | S15: 20.228574 | T15: 109.29466 | U15: 4.2152771 | V15: 80.950399 | W15: 2.6814298 | X15: 90.925119 | Y15: 31.465411 | Z15: 535.38472
A16: Catfish Smoked | C16: 4475.0964 | G16: 4352.7683 | H16: 8827.8647 | L16: Catfish :dried | O16: 4.4289155 | P16: 80.016754 | W16: 3.8823436 | X16: 76.63717 | Y16: 8.311259 | Z16: 156.65392
A17: Chicken feet | B17: 3502.697 | C17: 3397.8334 | D17: 3346.6242 | E17: 3293.6296 | F17: 3487.0588 | G17: 3336.7032 | H17: 20364.546 | L17: Catfish Smoked | O17: 2.8103499 | P17: 55.95907 | W17: 2.6599243 | X17: 54.546335 | Y17: 5.4702742 | Z17: 110.50541
A18: Chicken meat (Frozen) | B18: 5740.1492 | C18: 6473.8064 | D18: 5552.7027 | E18: 5497.0311 | F18: 5675.6757 | G18: 6130.5146 | H18: 35069.88 | L18: Chicken feet | M18: 0.44846575 | N18: 31.635946 | O18: 1.8320509 | P18: 74.199754 | Q18: 1.6090049 | R18: 44.656477 | S18: -3.0667712 | T18: 60.500418 | U18: 4.1963045 | V18: 42.891521 | W18: 2.1140435 | X18: 86.293617 | Y18: 7.1330983 | Z18: 340.17773
A19: Chicken Wings | B19: 4771.9237 | C19: 4422.8022 | D19: 4394.4054 | E19: 4340.1078 | F19: 4671.3133 | G19: 4316.4129 | H19: 26916.965 | L19: Chicken meat (Frozen) | M19: 1.1359629 | N19: 18.865061 | O19: 5.5997228 | P19: 71.654927 | Q19: 1.012757 | R19: 27.041398 | S19: -15.088114 | T19: 37.165941 | U19: 2.2146508 | V19: 24.341673 | W19: 2.6547057 | X19: 68.148553 | Y19: -2.4703147 | Z19: 247.21755
A20: Cray fish small white | B20: 6655.6615 | D20: 6440.4411 | E20: 6227.0407 | F20: 6657.0025 | H20: 25980.146 | L20: Chicken Wings | M20: 2.1537917 | N20: 43.288042 | O20: 2.4647605 | P20: 95.278567 | Q20: 1.2510657 | R20: 59.685989 | S20: -1.8697281 | T20: 73.132752 | U20: 6.3013744 | V20: 56.107344 | W20: 2.9195945 | X20: 110.91658 | Y20: 13.220859 | Z20: 438.40927
A21: Dried Fish Sardine | C21: 4908.4226 | G21: 4766.5639 | H21: 9674.9865 | L21: Cray fish small white | M21: -0.0201443 | Q21: 3.4269948 | U21: 3.3625252 | Y21: 6.7693757
A22: Dried fish, Bonga | B22: 6657.7428 | D22: 6160.0213 | E22: 6131.9801 | F22: 6493.7843 | H22: 25443.529 | L22: Dried Fish Sardine | O22: 2.9761217 | P22: 71.38544 | W22: 2.6846165 | X22: 73.271968 | Y22: 5.6607383 | Z22: 144.65741
A23: Garri white | B23: 1345.0979 | C23: 1184.7662 | D23: 1277.2471 | E23: 1267.6349 | F23: 1362.9593 | G23: 1205.3886 | H23: 7643.0939 | L23: Dried fish, Bonga | M23: 2.5248521 | Q23: 0.45729427 | U23: 5.4182121 | Y23: 8.4003584
A24: Garri Yellow | B24: 1422.3398 | C24: 1296.9267 | D24: 1378.1547 | E24: 1358.9584 | F24: 1456.6513 | G24: 1311.0287 | H24: 8224.0597 | L24: Garri white | M24: -1.3104914 | N24: 57.910811 | O24: -1.7108511 | P24: 108.32161 | Q24: 0.75827745 | R24: 76.549718 | S24: 6.9945192 | T24: 111.03078 | U24: 6.710702 | V24: 81.753895 | W24: 0.61278118 | X24: 119.58037 | Y24: 12.054937 | Z24: 555.14718
A25: Ginger, fresh | B25: 4970.6588 | D25: 4371.8969 | E25: 4206.7995 | F25: 4600.2308 | H25: 18149.586 | L25: Garri Yellow | M25: -2.3554998 | N25: 56.341298 | O25: -1.0756402 | P25: 116.60552 | Q25: 1.4125736 | R25: 82.88488 | S25: 4.7829754 | T25: 117.7076 | U25: 5.6957726 | V25: 81.172867 | W25: 3.531011 | X25: 125.61466 | Y25: 11.991193 | Z25: 580.32682 | AD25: TOP 10 INFLATION RANKING
A26: Goat Meat Bone in | B26: 6708.4528 | D26: 6298.8934 | E26: 6202.3575 | F26: 6892.4623 | H26: 26102.166 | L26: Ginger, fresh | M26: 8.0523791 | Q26: 3.9245368 | U26: 5.2227643 | Y26: 17.19968 | AD26: Row Labels | AE26: Average of YoY | AH26: TOP 10 HIGHEST INFLATION RANKING
A27: Groundnut oil, 75cl | B27: 3250.3191 | C27: 3328.1693 | D27: 3039.8295 | E27: 2939.7346 | F27: 3218.8178 | G27: 3165.3812 | H27: 18942.252 | L27: Goat Meat Bone in | M27: -2.6697214 | Q27: 1.5564387 | U27: 9.4233838 | Y27: 8.310101 | AD27: Local Rice (Broken) | AE27: 157.51878 | AH27: Row Labels | AI27: Count of Highest Price | AO27: TOP 10 STATE WITH HIGHEST INFLATION RATE | AP27: TOP 10 STATE WITH HIGHEST INFLATION RATE
A28: Groundnuts, roasted,75cl bottle | B28: 2545.7164 | D28: 2392.4711 | E28: 2387.7568 | F28: 2487.6765 | H28: 9813.6208 | L28: Groundnut oil, 75cl | M28: 0.97866058 | O28: 5.1427648 | P28: 84.186821 | Q28: 3.4048939 | U28: 5.8881052 | W28: 8.0734425 | X28: 82.026853 | Y28: 23.487867 | Z28: 166.21367 | AD28: Beans Brown | AE28: 143.28973 | AH28: Enugu | AI28: 25 | AO28: Row Labels | AP28: Count of Lowest Price
A29: Iced Sardine | C29: 4014.2349 | G29: 3875.6589 | H29: 7889.8938 | L29: Groundnuts, roasted,75cl bottle | M29: 2.3330977 | Q29: 0.19743431 | U29: 3.9793781 | Y29: 6.5099101 | AD29: Plantain (unripe) | AE29: 133.72148 | AH29: Imo | AI29: 22 | AO29: Abuja | AP29: 10
A30: Irish Potatoe | B30: 1948.6077 | C30: 1818.2876 | D30: 1756.4073 | E30: 1790.9109 | F30: 1881.7563 | G30: 1778.9605 | H30: 10974.93 | L30: Iced Sardine | O30: 3.5755458 | P30: 74.231669 | W30: 4.5527696 | X30: 74.344787 | Y30: 8.1283154 | Z30: 148.57646 | AD30: Agric hen eggs, (a Crate of 30 pieces) | AE30: 132.09737 | AH30: Plateau | AI30: 19 | AO30: Osun | AP30: 10
A31: Local Rice (Broken) | B31: 2517.8856 | C31: 2512.3265 | D31: 2564.9518 | E31: 2508.155 | F31: 2671.729 | G31: 2485.1389 | H31: 15260.187 | L31: Irish Potatoe | M31: 3.5526087 | N31: 37.850556 | O31: 2.2106818 | P31: 80.679153 | Q31: -1.9265956 | R31: 55.347702 | S31: -1.505634 | T31: 70.276157 | U31: 7.136671 | V31: 50.006412 | W31: 2.6237522 | X31: 103.86148 | Y31: 12.091484 | Z31: 398.02146 | AD31: Beans white | AE31: 126.05759 | AH31: Ebonyi | AI31: 19 | AO31: Kebbi | AP31: 11
A32: Mackerel, Frozen | B32: 5417.3963 | C32: 4287.654 | D32: 5233.1514 | E32: 5117.8059 | F32: 5482.6328 | G32: 4203.7598 | H32: 29742.4 | L32: Local Rice (Broken) | M32: -5.7581946 | O32: 1.0940094 | P32: 150.706 | Q32: 2.2644877 | U32: 4.1629298 | W32: 2.3260488 | X32: 164.33156 | Y32: 4.0892809 | Z32: 315.03756 | AD32: Rice Medium Grained | AE32: 117.94772 | AH32: Gombe | AI32: 15 | AO32: Kogi | AP32: 13
A33: Maize (Corn) Grains (White) sold loose | B33: 1239.6097 | C33: 1151.1347 | D33: 1169.321 | E33: 1168.338 | F33: 1278.7595 | G33: 1156.9086 | H33: 7164.0715 | L33: Mackerel, Frozen | M33: -1.1898743 | N33: 67.982055 | O33: 1.9956959 | P33: 89.201112 | Q33: 2.2538078 | R33: 92.978981 | S33: 19.361448 | T33: 108.21326 | U33: 4.7673251 | V33: 84.469122 | W33: 1.6347896 | X33: 90.64289 | Y33: 28.823192 | Z33: 533.48742 | AD33: Plantain (ripe) | AE33: 116.2034 | AH33: Ogun | AI33: 14 | AO33: Niger | AP33: 13
A34: Maize grain yellow sold loose | C34: 1160.2151 | G34: 1163.2443 | H34: 2323.4595 | L34: Maize (Corn) Grains (White) sold loose | M34: -3.0615498 | N34: 55.41565 | O34: -0.49908219 | P34: 99.237028 | Q34: 0.084139931 | R34: 60.301365 | S34: 1.494461 | T34: 84.306004 | U34: 9.3591501 | V34: 68.733508 | W34: 7.0773375 | X34: 107.58071 | Y34: 14.454457 | Z34: 475.57426 | AD34: Rice agric sold loose | AE34: 116.1475 | AH34: Akwa Ibom | AI34: 11 | AO34: Borno | AP34: 15
A35: Mudfish (aro) fresh | C35: 4166.6761 | G35: 4136.4787 | H35: 8303.1548 | L35: Maize grain yellow sold loose | O35: -0.26040698 | P35: 96.728586 | W35: 7.6166339 | X35: 108.02618 | Y35: 7.3562269 | Z35: 204.75477 | AD35: Yam Tuber | AE35: 114.98585 | AH35: Kwara | AI35: 11 | AO35: Benue | AP35: 16
A36: Mudfish : dried | C36: 5632.3371 | G36: 5345.9909 | H36: 10978.328 | L36: Mudfish (aro) fresh | O36: 0.73002725 | P36: 88.147628 | W36: 2.026348 | X36: 94.108678 | Y36: 2.7563752 | Z36: 182.25631 | AD36: Tilapia fresh fish (Epiya) | AE36: 105.83782 | AH36: Kogi | AI36: 10 | AO36: Taraba | AP36: 17
A37: Onions, fresh | B37: 1503.5645 | C37: 2057.8109 | D37: 1372.0419 | E37: 1367.6216 | F37: 1434.8498 | G37: 1878.0015 | H37: 9613.8902 | L37: Mudfish : dried | O37: 5.3562791 | P37: 79.516485 | W37: 4.009383 | X37: 79.233988 | Y37: 9.365662 | Z37: 158.75047 | AD37: Maize grain yellow sold loose | AE37: 102.37738 | AH37: Ekiti | AI37: 10 | AO37: Oyo | AP37: 18
A38: Palm oil, 75cl | B38: 2516.3572 | C38: 2582.348 | D38: 2384.1511 | E38: 2329.5428 | F38: 2511.7729 | G38: 2466.7871 | H38: 14790.959 | L38: Onions, fresh | M38: 4.7889796 | N38: 47.577102 | O38: 9.5745057 | P38: 111.73946 | Q38: 0.32321366 | R38: 49.850061 | S38: -33.539978 | T38: 55.200318 | U38: 4.5776972 | V38: 52.827851 | W38: 50.057212 | X38: 174.65061 | Y38: 35.78163 | Z38: 491.8454 | AD38: Agric hen eggs | AE38: 99.36031 | AH38: Grand Total | AI38: 156 | AO38: Adamawa | AP38: 21
A39: Plantain (ripe) | B39: 2057.3966 | C39: 1533.681 | D39: 1914.499 | E39: 1876.0259 | F39: 2002.5842 | G39: 1540.0464 | H39: 10924.233 | L39: Palm oil, 75cl | M39: 0.18251061 | N39: 53.994735 | O39: 4.684671 | P39: 81.17625 | Q39: 2.3441642 | R39: 52.687358 | S39: -9.7897415 | T39: 59.91669 | U39: 5.3529241 | V39: 60.404329 | W39: 14.895274 | X39: 80.036482 | Y39: 17.669802 | Z39: 388.21584 | AD39: Garri Yellow | AE39: 96.721137 | AO39: Yobe | AP39: 29
A40: Plantain (unripe) | B40: 2231.8083 | C40: 1550.1514 | D40: 2127.6713 | E40: 2119.0689 | F40: 2214.5653 | G40: 1566.2043 | H40: 11809.469 | L40: Plantain (ripe) | M40: 2.7370858 | N40: 103.89396 | O40: -0.41332773 | P40: 102.33499 | Q40: 2.0507792 | R40: 126.16629 | S40: 22.32178 | T40: 131.41758 | U40: 4.6009508 | V40: 111.38821 | W40: 2.1788988 | X40: 122.01937 | Y40: 33.476167 | Z40: 697.22039 | AD40: Garri white | AE40: 92.52453 | AO40: Grand Total | AP40: 173
A41: Rice agric sold loose | C41: 2037.3032 | G41: 2042.3537 | H41: 4079.6569 | L41: Plantain (unripe) | M41: 0.77861702 | N41: 123.08987 | O41: -1.0249546 | P41: 107.78524 | Q41: 0.405949 | R41: 147.69398 | S41: 36.700773 | T41: 160.9867 | U41: 4.0839961 | V41: 137.31969 | W41: 1.7242721 | X41: 125.45341 | Y41: 42.668653 | Z41: 802.3289 | AD41: Beef Bone in | AE41: 91.99809
A42: Rice Local, short-Grained | B42: 2144.0499 | C42: 1944.4039 | D42: 2088.8217 | E42: 2067.9978 | F42: 2242.6382 | G42: 1959.9828 | H42: 12447.894 | L42: Rice agric sold loose | O42: -0.24728468 | P42: 109.49962 | W42: 0.92256514 | X42: 122.79538 | Y42: 0.67528045 | Z42: 232.295 | AD42: Bread (sliced), 450g | AE42: 91.676148
A43: Rice Long-Grained (Imported) | B43: 2574.1148 | C43: 2520.7757 | D43: 2565.0915 | E43: 2505.4794 | F43: 2679.506 | G43: 2489.1473 | H43: 15334.115 | L43: Rice Local, short-Grained | M43: -4.3960884 | N43: 53.218563 | O43: -0.79484759 | P43: 111.82372 | Q43: 1.0069575 | R43: 70.79957 | S43: 6.3563915 | T43: 102.39056 | U43: 7.3637945 | V43: 67.268219 | W43: 0.78878726 | X43: 126.01696 | Y43: 10.324995 | Z43: 531.5176 | AD43: Mudfish (aro) fresh | AE43: 91.128153
A44: Rice Medium Grained | C44: 2092.3906 | G44: 2104.4347 | H44: 4196.8253 | L44: Rice Long-Grained (Imported) | M44: -3.933231 | N44: 45.301865 | O44: 1.2706531 | P44: 105.56063 | Q44: 2.3792674 | R44: 65.543193 | S44: -0.60681026 | T44: 89.521087 | U44: 4.4604471 | V44: 63.990886 | W44: 0.72284973 | X44: 118.84482 | Y44: 4.2931761 | Z44: 488.76248 | AD44: Titus, frozen | AE44: 90.490071
A45: Semovita, Prepacked (1kg) | B45: 2257.1982 | D45: 2089.7944 | E45: 2072.0012 | F45: 2173.1179 | H45: 8592.1116 | L45: Rice Medium Grained | O45: -0.57232143 | P45: 111.1216 | W45: 1.7521342 | X45: 124.77385 | Y45: 1.1798128 | Z45: 235.89545 | AD45: Cat fresh fish | AE45: 89.230786
A46: Smoked fish (Mackerel) | B46: 5920.8373 | D46: 5458.019 | E46: 5407.6327 | F46: 5752.7551 | H46: 22539.244 | L46: Semovita, Prepacked (1kg) | M46: 3.8691088 | Q46: 0.85874402 | U46: 3.9871626 | Y46: 8.7150154 | AD46: Mackerel, Frozen | AE46: 88.91457
A47: Sweet potatoes | B47: 938.42378 | C47: 930.78901 | D47: 823.2987 | E47: 852.51531 | F47: 909.88488 | G47: 942.23834 | H47: 5397.15 | L47: Smoked fish (Mackerel) | M47: 2.921768 | Q47: 0.93176257 | U47: 5.4000572 | Y47: 9.2535878 | AD47: Rice Local, short-Grained | AE47: 88.586266
A48: Tilapia fresh fish (Epiya) | B48: 5489.282 | C48: 4106.7162 | D48: 5103.942 | E48: 5065.3632 | F48: 5459.0421 | G48: 4039.6253 | H48: 29263.971 | L48: Sweet potatoes | M48: 3.1365402 | N48: 16.235217 | O48: -1.215121 | P48: 68.64462 | Q48: -3.427107 | R48: 22.363804 | S48: -8.409392 | T48: 38.513938 | U48: 10.516982 | V48: 31.969207 | W48: 4.8642105 | X48: 91.978924 | Y48: 5.4661132 | Z48: 269.70571 | AD48: Bread (unsliced), 450g | AE48: 86.133272
A49: Tin Milk-Evaporated, Peak Milk, 150g | B49: 994.19174 | C49: 1014.7415 | D49: 931.03473 | E49: 928.00163 | F49: 999.17967 | G49: 991.20399 | H49: 5858.3532 | L49: Tilapia fresh fish (Epiya) | M49: 0.55394117 | N49: 94.044718 | O49: 1.6608209 | P49: 99.400453 | Q49: 0.76162036 | R49: 108.72778 | S49: 23.343395 | T49: 128.7436 | U49: 6.9573697 | V49: 100.06509 | W49: 2.4143523 | X49: 104.04528 | Y49: 35.6915 | Z49: 635.02692 | AD49: Tin Milk-Evaporated, Three Crown Milk, 160g | AE49: 83.94593
A50: Tin Milk-Evaporated, Three Crown Milk, 160g | B50: 888.91037 | C50: 887.45091 | D50: 827.31484 | E50: 837.23255 | F50: 872.13527 | G50: 873.77102 | H50: 5186.815 | L50: Tin Milk-Evaporated, Peak Milk, 150g | M50: -0.49920334 | N50: 36.990129 | O50: 2.3746346 | P50: 87.220903 | Q50: 0.32684271 | R50: 46.38922 | S50: -8.547974 | T50: 61.172096 | U50: 7.3192694 | V50: 49.196117 | W50: 3.7120168 | X50: 88.145187 | Y50: 4.6855862 | Z50: 369.11365 | AD50: Groundnut oil, 75cl | AE50: 83.106837
A51: Titus, frozen | B51: 5939.2873 | C51: 4725.1654 | D51: 5564.2891 | E51: 5467.2313 | F51: 5860.0071 | G51: 4626.8187 | H51: 32182.799 | L51: Tin Milk-Evaporated, Three Crown Milk, 160g | M51: 1.9234515 | O51: 1.5656151 | P51: 81.876076 | Q51: -1.1845821 | U51: 5.4175779 | W51: 3.6242693 | X51: 86.015784 | Y51: 11.346332 | Z51: 167.89186 | AD51: Onions, fresh | AE51: 81.974234
A52: Tomatoes, fresh | B52: 1283.5712 | C52: 1453.4957 | D52: 1111.1396 | E52: 1081.4391 | F52: 1157.3457 | G52: 1472.176 | H52: 7559.1674 | L52: Titus, frozen | M52: 1.3529022 | N52: 74.939647 | O52: 2.1255807 | P52: 88.091455 | Q52: 1.7752629 | R52: 92.998497 | S52: 15.704549 | T52: 107.99752 | U52: 5.3145702 | V52: 87.577591 | W52: 2.6042275 | X52: 91.33572 | Y52: 28.877092 | Z52: 542.94043 | AD52: Rice Long-Grained (Imported) | AE52: 81.460414
A53: Vegetable Oil, 75cl | B53: 3374.8094 | C53: 3362.8341 | D53: 3090.5104 | E53: 2975.9619 | F53: 3337.0083 | G53: 3147.0489 | H53: 19288.173 | L53: Tomatoes, fresh | M53: 10.906464 | N53: 14.256346 | O53: -1.2688953 | P53: 78.527096 | Q53: 2.7463822 | R53: 18.477526 | S53: -25.597361 | T53: 27.941863 | U53: 4.1584452 | V53: 20.596602 | W53: 0.4222524 | X53: 94.052697 | Y53: -8.6327123 | Z53: 253.85213 | AD53: Wheat Flour, Prepacked (2kg) | AE53: 80.941847
A54: Watermelon whole, medium size fresh | B54: 2057.3488 | D54: 1926.2041 | E54: 1850.8433 | F54: 2040.8187 | H54: 7875.2149 | L54: Vegetable Oil, 75cl | M54: 1.1327851 | N54: 62.390321 | O54: 6.8567464 | P54: 96.708633 | Q54: 3.8491239 | R54: 64.49277 | S54: -11.504348 | T54: 66.928959 | U54: 7.9759613 | V54: 66.5468 | W54: 15.735862 | X54: 95.446575 | Y54: 24.04613 | Z54: 452.51406 | AD54: Mudfish : dried | AE54: 79.375237
A55: Wheat Flour, Prepacked (2kg) | B55: 4166.5682 | C55: 3871.4754 | D55: 3890.803 | E55: 3847.3657 | F55: 4114.2425 | G55: 3819.3696 | H55: 23709.824 | L55: Watermelon whole, medium size fresh | M55: 0.80997257 | Q55: 4.0717035 | U55: 5.9502839 | Y55: 10.83196 | AD55: Maize (Corn) Grains (White) sold loose | AE55: 79.262377
A56: Yam Tuber | B56: 2240.0838 | C56: 1905.901 | D56: 2022.0329 | E56: 1991.3299 | F56: 2141.13 | G56: 1836.0085 | H56: 12136.486 | L56: Wheat Flour, Prepacked (2kg) | M56: 1.2718177 | N56: 61.918558 | O56: 1.3642522 | P56: 95.866203 | Q56: 1.1290142 | R56: 70.830139 | S56: -0.62275338 | T56: 88.320896 | U56: 5.7427615 | V56: 66.055531 | W56: 1.907862 | X56: 102.65976 | Y56: 10.792954 | Z56: 485.65108 | AD56: Catfish :dried | AE56: 78.326962
A57: Grand Total | B57: 135492.52 | C57: 125565.41 | D57: 127998.55 | E57: 125983.83 | F57: 136203.29 | G57: 123072.07 | H57: 774315.67 | L57: Yam Tuber | M57: 4.6215662 | N57: 98.172751 | O57: 3.8067597 | P57: 132.73389 | Q57: 1.5418325 | R57: 100.28933 | S57: 4.4823399 | T57: 120.78247 | U57: 5.8899696 | V57: 100.33469 | W57: 7.6469455 | X57: 137.60197 | Y57: 27.989413 | Z57: 689.91511 | AD57: Vegetable Oil, 75cl | AE57: 75.41901
L58: Grand Total | M58: 4.2892087 | N58: 1578.273 | O58: 61.830208 | P58: 4256.1287 | Q58: 57.876018 | R58: 1972.8883 | S58: 29.410614 | T58: 2491.4434 | U58: 253.09791 | V58: 1911.6636 | W58: 196.00161 | X58: 4671.5216 | Y58: 602.50557 | Z58: 16881.919 | AD58: Iced Sardine | AE58: 74.288228
AD59: Beef Boneless | AE59: 73.336427
AD60: Chicken Wings | AE60: 73.068212
AD61: Dried Fish Sardine | AE61: 72.328704
AD62: Irish Potatoe | AE62: 66.33691
AD63: Palm oil, 75cl | AE63: 64.702641
AD64: Tin Milk-Evaporated, Peak Milk, 150g | AE64: 61.518942
AD65: Chicken feet | AE65: 56.696289
AD66: Catfish Smoked | AE66: 55.252703
AD67: Sweet potatoes | AE67: 44.950952
AD68: Tomatoes, fresh | AE68: 42.308688
AD69: Chicken meat (Frozen) | AE69: 41.202925
AD70: Groundnuts, roasted,75cl bottle
AD71: Smoked fish (Mackerel)
AD72: Cray fish small white
AD73: Semovita, Prepacked (1kg)
AD74: Watermelon whole, medium size fresh
AD75: Ginger, fresh
AD76: Carrots, fresh
AD77: Dried fish, Bonga
AD78: Goat Meat Bone in
AD79: Grand Total | AE79: 87.020199

Sheet Standardized Data
A1: Month | B1: Standardized Item | C1: Item Label | D1: Match Confidence | E1: Avg (Same Month Last Year) | F1: Avg (Previous Month) | G1: Avg (Current Month) | H1: MoM | I1: YoY | J1: Highest | K1: Highest State | L1: Highest Price | M1: Lowest | N1: Lowest State | O1: Lowest Price | P1: Source File
A2: Nov-2024 | B2: Agric hen eggs | C2: Agric eggs(medium size price of one) | D2: Confirmed | E2: 110.09887 | F2: 235.6735 | G2: 247.2591 | H2: 4.9159544 | I2: 124.57914 | J2: Gombe (300) | K2: Gombe | L2: 300 | M2: Borno (199.73) | N2: Borno | O2: 199.73 | P2: selected_food_Nov_2024.xlsx
A3: Dec-2024 | B3: Agric hen eggs | C3: Agric eggs(medium size price of one) | D3: Confirmed | E3: 110.04436 | F3: 247.2591 | G3: 252.1655 | H3: 1.9843144 | I3: 129.14896 | J3: Bauchi (300.73) | K3: Bauchi | L3: 300.73 | M3: Taraba (212) | N3: Taraba | O3: 212 | P3: selected_food_Dec_2024.xlsx
A4: Jan-2025 | B4: Agric hen eggs | C4: Agric hen eggs | D4: Confirmed | E4: 116.41 | F4: 252.1655 | G4: 248.04139 | H4: -1.6354765 | I4: 113.07567 | J4: Enugu (325) | K4: Enugu | L4: 325 | M4: Adamawa (200) | N4: Adamawa | O4: 200 | P4: Selected_food_table_Jan25.xlsx
A5: Feb-2025 | B5: Agric hen eggs | C5: Agric hen eggs, | D5: Confirmed | E5: 139.28021 | F5: 248.04139 | G5: 251.94052 | H5: 1.5719659 | I5: 80.887516 | J5: Enugu (325) | K5: Enugu | L5: 325 | M5: Adamawa (200) | N5: Adamawa | O5: 200 | P5: selected_food_table_Feb_25.xlsx
A6: Mar-2025 | B6: Agric hen eggs | C6: Agric hen eggs, | D6: Confirmed | E6: 147.92334 | F6: 251.94052 | G6: 261.18235 | H6: 3.6682586 | I6: 76.566018 | J6: Enugu (354.75) | K6: Enugu | L6: 354.75 | M6: Kaduna (210) | N6: Kaduna | O6: 210 | P6: selected_food_table_Mar_25.xlsx
A7: Apr-2025 | B7: Agric hen eggs | C7: Agric hen eggs, | D7: Confirmed | E7: 150.84891 | F7: 261.18235 | G7: 259.31615 | H7: -0.7145176 | I7: 71.904558 | J7: Enugu (356.73) | K7: Enugu | L7: 356.73 | M7: Kaduna (220) | N7: Kaduna | O7: 220 | P7: selected_food_table_Apr25.xlsx
A8: Nov-2024 | B8: Agric hen eggs, (a Crate of 30 pieces) | C8: Agric eggs medium size | D8: Likely | E8: 1202.1768 | F8: 2671.6021 | G8: 2833.973 | H8: 6.0776605 | I8: 135.7368 | J8: Gombe (3600) | K8: Gombe | L8: 3600 | M8: Borno (2381.15) | N8: Borno | O8: 2381.15 | P8: selected_food_Nov_2024.xlsx
A9: Dec-2024 | B9: Agric hen eggs, (a Crate of 30 pieces) | C9: Agric eggs medium size | D9: Likely | E9: 1254.8984 | F9: 2833.973 | G9: 2866.9151 | H9: 1.162399 | I9: 128.45794 | J9: Gombe (3600.65) | K9: Gombe | L9: 3600.65 | M9: Borno (2431.2) | N9: Borno | O9: 2431.2 | P9: selected_food_Dec_2024.xlsx
A10: Jan-2025 | B10: Agric hen eggs, (a Crate of 30 pieces) | C10: Agric hen eggs, (a Crate of 30 pieces) | D10: Likely | G10: 5878.1406 | J10: Enugu (7000) | K10: Enugu | L10: 7000 | M10: Niger (4613.06) | N10: Niger | O10: 4613.06 | P10: Selected_food_table_Jan25.xlsx
A11: Feb-2025 | B11: Agric hen eggs, (a Crate of 30 pieces) | C11: Agric hen eggs, (a Crate of 30 pieces) | D11: Likely | F11: 5878.1406 | G11: 5976.1159 | H11: 1.666772 | J11: Enugu (7250) | K11: Enugu | L11: 7250 | M11: Kogi (5000) | N11: Kogi | O11: 5000 | P11: selected_food_table_Feb_25.xlsx
A12: Mar-2025 | B12: Agric hen eggs, (a Crate of 30 pieces) | C12: Agric hen eggs, (a Crate of 30 pieces) | D12: Likely | F12: 5976.1159 | G12: 7670.5592 | H12: 28.353589 | J12: Enugu (7930) | K12: Enugu | L12: 7930 | M12: Niger (5300) | N12: Niger | O12: 5300 | P12: selected_food_table_Mar_25.xlsx
A13: Apr-2025 | B13: Agric hen eggs, (a Crate of 30 pieces) | C13: Agric hen eggs, (a Crate of 30 pieces) | D13: Likely | F13: 7670.5592 | G13: 6150.1781 | H13: -19.820995 | J13: Enugu (7869.33) | K13: Enugu | L13: 7869.33 | M13: Jigawa (540) | N13: Jigawa | O13: 540 | P13: selected_food_table_Apr25.xlsx
A14: Nov-2024 | B14: Beans Brown | C14: Beans brown,sold loose | D14: Confirmed | E14: 838.84915 | F14: 2798.4962 | G14: 2720.9608 | H14: -2.7706082 | I14: 224.36831 | J14: Bauchi (3675) | K14: Bauchi | L14: 3675 | M14: Adamawa (1925) | N14: Adamawa | O14: 1925 | P14: selected_food_Nov_2024.xlsx
A15: Dec-2024 | B15: Beans Brown | C15: Beans brown,sold loose | D15: Confirmed | E15: 870.66795 | F15: 2720.9608 | G15: 2501.3235 | H15: -8.0720499 | I15: 187.28788 | J15: Bauchi (3500.32) | K15: Bauchi | L15: 3500.32 | M15: Yobe (1755.63) | N15: Yobe | O15: 1755.63 | P15: selected_food_Dec_2024.xlsx
A16: Jan-2025 | B16: Beans Brown | C16: Beans Brown | D16: Confirmed | E16: 976.58407 | F16: 2501.3235 | G16: 2458.5333 | H16: -1.7107038 | I16: 151.74825 | J16: Abia (3230.87) | K16: Abia | L16: 3230.87 | M16: Sokoto (1575.36) | N16: Sokoto | O16: 1575.36 | P16: Selected_food_table_Jan25.xlsx
A17: Feb-2025 | B17: Beans Brown | C17: Beans Brown | D17: Confirmed | E17: 1177.9258 | F17: 2458.5333 | G17: 2465.9628 | H17: 0.30219169 | I17: 109.34789 | J17: Ebonyi (3200) | K17: Ebonyi | L17: 3200 | M17: Sokoto (1572.83) | N17: Sokoto | O17: 1572.83 | P17: selected_food_table_Feb_25.xlsx
A18: Mar-2025 | B18: Beans Brown | C18: Beans Brown | D18: Confirmed | E18: 1234.4022 | F18: 2465.9628 | G18: 2616.2636 | H18: 6.0950166 | I18: 111.9458 | J18: Abia (3651.13) | K18: Abia | L18: 3651.13 | M18: Sokoto (1634.36) | N18: Sokoto | O18: 1634.36 | P18: selected_food_table_Mar_25.xlsx
A19: Apr-2025 | B19: Beans Brown | C19: Beans Brown | D19: Confirmed | E19: 1387.903 | F19: 2616.2636 | G19: 2429.3886 | H19: -7.1428215 | I19: 75.040225 | J19: Abia (3600) | K19: Abia | L19: 3600 | M19: Sokoto (1658.02) | N19: Sokoto | O19: 1658.02 | P19: selected_food_table_Apr25.xlsx
A20: Nov-2024 | B20: Beans white | C20: Beans:white black eye. sold loose | D20: Confirmed | E20: 800.48677 | F20: 2603.318 | G20: 2546.7025 | H20: -2.1747433 | I20: 218.14424 | J20: Ebonyi (3157.2) | K20: Ebonyi | L20: 3157.2 | M20: Adamawa (1750) | N20: Adamawa | O20: 1750 | P20: selected_food_Nov_2024.xlsx
A21: Dec-2024 | B21: Beans white | C21: Beans:white black eye. sold loose | D21: Confirmed | E21: 829.86193 | F21: 2546.7025 | G21: 2319.0422 | H21: -8.9394163 | I21: 179.44916 | J21: Abuja (3176.63) | K21: Abuja | L21: 3176.63 | M21: Yobe (1534.59) | N21: Yobe | O21: 1534.59 | P21: selected_food_Dec_2024.xlsx
A22: Jan-2025 | B22: Beans white | C22: Beans white | D22: Confirmed | E22: 921.37822 | F22: 2319.0422 | G22: 2123.853 | H22: -8.4168028 | I22: 130.50827 | J22: Enugu (2722.76) | K22: Enugu | L22: 2722.76 | M22: Sokoto (1370.59) | N22: Sokoto | O22: 1370.59 | P22: Selected_food_table_Jan25.xlsx
A23: Feb-2025 | B23: Beans white | C23: Beans white | D23: Confirmed | E23: 1156.8221 | F23: 2123.853 | G23: 2114.3292 | H23: -0.44841891 | I23: 82.770467 | J23: Abia (2825.33) | K23: Abia | L23: 2825.33 | M23: Yobe (1371.48) | N23: Yobe | O23: 1371.48 | P23: selected_food_table_Feb_25.xlsx
A24: Mar-2025 | B24: Beans white | C24: Beans white | D24: Confirmed | E24: 1192.2158 | F24: 2114.3292 | G24: 2215.1071 | H24: 4.7664205 | I24: 85.79749 | J24: Enugu (3122.19) | K24: Enugu | L24: 3122.19 | M24: Abuja (1521.57) | N24: Abuja | O24: 1521.57 | P24: selected_food_table_Mar_25.xlsx
A25: Apr-2025 | B25: Beans white | C25: Beans white | D25: Confirmed | E25: 1313.479 | F25: 2215.1071 | G25: 2097.3099 | H25: -5.3178976 | I25: 59.675942 | J25: Enugu (3100) | K25: Enugu | L25: 3100 | M25: Kaduna (1503.96) | N25: Kaduna | O25: 1503.96 | P25: selected_food_table_Apr25.xlsx
... A35: Dec-2024 | B35: Bread (sliced), 450g | C35: Bread sliced 500g | D35: Likely | E35: 855.04746 | F35: 1588.0267 | G35: 1610.8262 | H35: 1.4357127 | I35: 88.390264 | J35: Akwa Ibom (1890) | K35: Akwa Ibom | L35: 1890 | M35: Benue (1299.01) | N35: Benue | O35: 1299.01 | P35: selected_food_Dec_2024.xlsx
A36: Jan-2025 | B36: Bread (sliced), 450g | C36: Bread (sliced), 450g | D36: Likely | G36: 1604.7842 | J36: Ogun (1950) | K36: Ogun | L36: 1950 | M36: Osun (1300) | N36: Osun | O36: 1300 | P36: Selected_food_table_Jan25.xlsx
A37: Feb-2025 | B37: Bread (sliced), 450g | C37: Bread (sliced), 450g | D37: Likely | F37: 1604.7842 | G37: 1633.1854 | H37: 1.7697791 | J37: Ogun (1950) | K37: Ogun | L37: 1950 | M37: Osun (1256.25) | N37: Osun | O37: 1256.25 | P37: selected_food_table_Feb_25.xlsx
A38: Mar-2025 | B38: Bread (sliced), 450g | C38: Bread (sliced), 450g | D38: Likely | F38: 1633.1854 | G38: 1680.1747 | H38: 2.8771572 | J38: Ogun (2187.92) | K38: Ogun | L38: 2187.92 | M38: Osun (1256.25) | N38: Osun | O38: 1256.25 | P38: selected_food_table_Mar_25.xlsx
A39: Apr-2025 | B39: Bread (sliced), 450g | C39: Bread (sliced), 450g | D39: Likely | F39: 1680.1747 | G39: 1688.3998 | H39: 0.48954126 | J39: Ogun (2187.92) | K39: Ogun | L39: 2187.92 | M39: Osun (1256.25) | N39: Osun | O39: 1256.25 | P39: selected_food_table_Apr25.xlsx
A40: Nov-2024 | B40: Bread (unsliced), 450g | C40: Bread unsliced 500g | D40: Likely | E40: 795.82989 | F40: 1454.4362 | G40: 1486.2466 | H40: 2.1871298 | I40: 86.754307 | J40: Delta (1805.42) | K40: Delta | L40: 1805.42 | M40: Borno (1053.56) | N40: Borno | O40: 1053.56 | P40: selected_food_Nov_2024.xlsx
A41: Dec-2024 | B41: Bread (unsliced), 450g | C41: Bread unsliced 500g | D41: Likely | E41: 815.10931 | F41: 1486.2466 | G41: 1512.1275 | H41: 1.7413605 | I41: 85.512238 | J41: Delta (1823.75) | K41: Delta | L41: 1823.75 | M41: Yobe (1112.87) | N41: Yobe | O41: 1112.87 | P41: selected_food_Dec_2024.xlsx
A42: Jan-2025 | B42: Bread (unsliced), 450g | C42: Bread (unsliced), 450g | D42: Likely | G42: 1452.983 | J42: Akwa Ibom (1800) | K42: Akwa Ibom | L42: 1800 | M42: Yobe (900) | N42: Yobe | O42: 900 | P42: Selected_food_table_Jan25.xlsx
A43: Feb-2025 | B43: Bread (unsliced), 450g | C43: Bread (unsliced), 450g | D43: Likely | F43: 1452.983 | G43: 1497.4272 | H43: 3.0588232 | J43: Akwa Ibom (1900) | K43: Akwa Ibom | L43: 1900 | M43: Yobe (900) | N43: Yobe | O43: 900 | P43: selected_food_table_Feb_25.xlsx
A44: Mar-2025 | B44: Bread (unsliced), 450g | C44: Bread (unsliced), 450g | D44: Likely | F44: 1497.4272 | G44: 1561.2438 | H44: 4.2617539 | J44: Ebonyi (1908.56) | K44: Ebonyi | L44: 1908.56 | M44: Yobe (960) | N44: Yobe | O44: 960 | P44: selected_food_table_Mar_25.xlsx
A45: Apr-2025 | B45: Bread (unsliced), 450g | C45: Bread (unsliced), 450g | D45: Likely | F45: 1561.2438 | G45: 1547.5179 | H45: -0.87916515 | J45: Ebonyi (1922.3) | K45: Ebonyi | L45: 1922.3 | M45: Ekiti (1000) | N45: Ekiti | O45: 1000 | P45: selected_food_table_Apr25.xlsx
A46: Jan-2025 | B46: Carrots, fresh | C46: Carrots, fresh | D46: New (2025) | G46: 1787.1615 | J46: Bayelsa (2572.73) | K46: Bayelsa | L46: 2572.73 | M46: Benue (1400) | N46: Benue | O46: 1400 | P46: Selected_food_table_Jan25.xlsx
A47: Feb-2025 | B47: Carrots, fresh | C47: Carrots, fresh | D47: New (2025) | F47: 1787.1615 | G47: 1838.5928 | H47: 2.8778248 | J47: Imo (2557.14) | K47: Imo | L47: 2557.14 | M47: Zamfara (1410) | N47: Zamfara | O47: 1410 | P47: selected_food_table_Feb_25.xlsx
A48: Mar-2025 | B48: Carrots, fresh | C48: Carrots, fresh | D48: New (2025) | F48: 1838.5928 | G48: 1947.0497 | H48: 5.8989086 | J48: Imo (2980.7) | K48: Imo | L48: 2980.7 | M48: Zamfara (1450) | N48: Zamfara | O48: 1450 | P48: selected_food_table_Mar_25.xlsx
A49: Apr-2025 | B49: Carrots, fresh | C49: Carrots, fresh | D49: New (2025) | F49: 1947.0497 | G49: 1931.3179 | H49: -0.80798556 | J49: Imo (3000) | K49: Imo | L49: 3000 | M49: Borno (1200) | N49: Borno | O49: 1200 | P49: selected_food_table_Apr25.xlsx
A50: Nov-2024 | B50: Cat fresh fish | C50: Catfish (obokun) fresh | D50: Confirmed | E50: 2231.2344 | F50: 4148.7414 | G50: 4259.987 | H50: 2.6814298 | I50: 90.925119 | J50: Bayelsa (5885.71) | K50: Bayelsa | L50: 5885.71 | M50: Adamawa (3000) | N50: Adamawa | O50: 3000 | P50: selected_food_Nov_2024.xlsx
A51: Dec-2024 | B51: Cat fresh fish | C51: Catfish (obokun) fresh | D51: Confirmed | E51: 2347.4083 | F51: 4259.987 | G51: 4347.4446 | H51: 2.0530016 | I51: 85.20189 | J51: Bayelsa (5815.86) | K51: Bayelsa | L51: 5815.86 | M51: Nasarawa (3110.1) | N51: Nasarawa | O51: 3110.1 | P51: selected_food_Dec_2024.xlsx
A52: Jan-2025 | B52: Cat fresh fish | C52: Cat fresh fish | D52: Confirmed | E52: 2497.3741 | F52: 4347.4446 | G52: 5226.8706 | H52: 20.228574 | I52: 109.29466 | J52: Plateau (7608.1) | K52: Plateau | L52: 7608.1 | M52: Kaduna (3442.5) | N52: Kaduna | O52: 3442.5 | P52: Selected_food_table_Jan25.xlsx
A53: Feb-2025 | B53: Cat fresh fish | C53: Cat fresh fish | D53: Confirmed | E53: 2758.3787 | F53: 5226.8706 | G53: 5284.3595 | H53: 1.0998735 | I53: 91.574837 | J53: Plateau (7608.1) | K53: Plateau | L53: 7608.1 | M53: Kaduna (3500) | N53: Kaduna | O53: 3500 | P53: selected_food_table_Feb_25.xlsx
A54: Mar-2025 | B54: Cat fresh fish | C54: Cat fresh fish | D54: Confirmed | E54: 3043.4362 | F54: 5284.3595 | G54: 5507.1099 | H54: 4.2152771 | I54: 80.950399 | J54: Plateau (8213.1) | K54: Plateau | L54: 8213.1 | M54: Zamfara (3590) | N54: Zamfara | O54: 3590 | P54: selected_food_table_Mar_25.xlsx
A55: Apr-2025 | B55: Cat fresh fish | C55: Cat fresh fish | D55: Confirmed | E55: 3140.5331 | F55: 5507.1099 | G55: 5572.4934 | H55: 1.1872558 | I55: 77.437818 | J55: Plateau (8213.1) | K55: Plateau | L55: 8213.1 | M55: Zamfara (3615.22) | N55: Zamfara | O55: 3615.22 | P55: selected_food_table_Apr25.xlsx
A56: Nov-2024 | B56: Catfish :dried | C56: Catfish :dried | D56: Discontinued | E56: 3276.6289 | F56: 5571.442 | G56: 5787.7445 | H56: 3.8823436 | I56: 76.63717 | J56: Imo (12181.27) | K56: Imo | L56: 12181.27 | M56: Kano (3950.44) | N56: Kano | O56: 3950.44 | P56: selected_food_Nov_2024.xlsx
A57: Dec-2024 | B57: Catfish :dried | C57: Catfish :dried | D57: Discontinued | E57: 3357.509 | F57: 5787.7445 | G57: 6044.0788 | H57: 4.4289155 | I57: 80.016754 | J57: Imo (12478.59) | K57: Imo | L57: 12478.59 | M57: Katsina (4100.14) | N57: Katsina | O57: 4100.14 | P57: selected_food_Dec_2024.xlsx
A58: Nov-2024 | B58: Catfish Smoked | C58: Catfish Smoked | D58: Discontinued | E58: 2816.4811 | F58: 4239.9879 | G58: 4352.7683 | H58: 2.6599243 | I58: 54.546335 | J58: Yobe (6255.22) | K58: Yobe | L58: 6255.22 | M58: Kebbi (3391.67) | N58: Kebbi | O58: 3391.67 | P58: selected_food_Nov_2024.xlsx
A59: Dec-2024 | B59: Catfish Smoked | C59: Catfish Smoked | D59: Discontinued | E59: 2869.4044 | F59: 4352.7683 | G59: 4475.0964 | H59: 2.8103499 | I59: 55.95907 | J59: Yobe (7142.86) | K59: Yobe | L59: 7142.86 | M59: Kebbi (3310.57) | N59: Kebbi | O59: 3310.57 | P59: selected_food_Dec_2024.xlsx
A60: Nov-2024 | B60: Chicken Wings | C60: Chicken Wings | D60: Confirmed | E60: 2046.5024 | F60: 4193.9661 | G60: 4316.4129 | H60: 2.9195945 | I60: 110.91658 | J60: Ondo (6100) | K60: Ondo | L60: 6100 | M60: Adamawa (2200) | N60: Adamawa | O60: 2200 | P60: selected_food_Nov_2024.xlsx
A61: Dec-2024 | B61: Chicken Wings | C61: Chicken Wings | D61: Confirmed | E61: 2264.8682 | F61: 4316.4129 | G61: 4422.8022 | H61: 2.4647605 | I61: 95.278567 | J61: Ondo (6120) | K61: Ondo | L61: 6120 | M61: Adamawa (2300) | N61: Adamawa | O61: 2300 | P61: selected_food_Dec_2024.xlsx
... A77: Apr-2025 | B77: Chicken meat (Frozen) | C77: Chicken meat (Frozen) | D77: Confirmed | E77: 4829.1308 | F77: 5675.6757 | G77: 5740.1492 | H77: 1.1359629 | I77: 18.865061 | J77: Enugu (8216.56) | K77: Enugu | L77: 8216.56 | M77: Gombe (4600) | N77: Gombe | O77: 4600 | P77: selected_food_table_Apr25.xlsx
A78: Jan-2025 | B78: Cray fish small white | C78: Cray fish small white | D78: New (2025) | G78: 6227.0407 | J78: Abuja (7800) | K78: Abuja | L78: 7800 | M78: Bayelsa (4000) | N78: Bayelsa | O78: 4000 | P78: Selected_food_table_Jan25.xlsx
A79: Feb-2025 | B79: Cray fish small white | C79: Cray fish small white | D79: New (2025) | F79: 6227.0407 | G79: 6440.4411 | H79: 3.4269948 | J79: Kogi (8000) | K79: Kogi | L79: 8000 | M79: Bayelsa (4300) | N79: Bayelsa | O79: 4300 | P79: selected_food_table_Feb_25.xlsx
A80: Mar-2025 | B80: Cray fish small white | C80: Cray fish small white | D80: New (2025) | F80: 6440.4411 | G80: 6657.0025 | H80: 3.3625252 | J80: Kogi (8000) | K80: Kogi | L80: 8000 | M80: Bayelsa (4500) | N80: Bayelsa | O80: 4500 | P80: selected_food_table_Mar_25.xlsx
A81: Apr-2025 | B81: Cray fish small white | C81: Cray fish small white | D81: New (2025) | F81: 6657.0025 | G81: 6655.6615 | H81: -0.0201443 | J81: Kogi (8000) | K81: Kogi | L81: 8000 | M81: Akwa Ibom (4576.03) | N81: Akwa Ibom | O81: 4576.03 | P81: selected_food_table_Apr25.xlsx
A82: Nov-2024 | B82: Dried Fish Sardine | C82: Dried Fish Sardine | D82: Discontinued | E82: 2750.9146 | F82: 4641.9454 | G82: 4766.5639 | H82: 2.6846165 | I82: 73.271968 | J82: Nasarawa (7474.67) | K82: Nasarawa | L82: 7474.67 | M82: Niger (2900.57) | N82: Niger | O82: 2900.57 | P82: selected_food_Nov_2024.xlsx
A83: Dec-2024 | B83: Dried Fish Sardine | C83: Dried Fish Sardine | D83: Discontinued | E83: 2863.9671 | F83: 4766.5639 | G83: 4908.4226 | H83: 2.9761217 | I83: 71.38544 | J83: Nasarawa (7669.01) | K83: Nasarawa | L83: 7669.01 | M83: Niger (2903.57) | N83: Niger | O83: 2903.57 | P83: selected_food_Dec_2024.xlsx
A84: Jan-2025 | B84: Dried fish, Bonga | C84: Dried fish, Bonga | D84: New (2025) | G84: 6131.9801 | J84: Enugu (8900) | K84: Enugu | L84: 8900 | M84: Bayelsa (4202.78) | N84: Bayelsa | O84: 4202.78 | P84: Selected_food_table_Jan25.xlsx
A85: Feb-2025 | B85: Dried fish, Bonga | C85: Dried fish, Bonga | D85: New (2025) | F85: 6131.9801 | G85: 6160.0213 | H85: 0.45729427 | J85: Enugu (9000) | K85: Enugu | L85: 9000 | M85: Adamawa (4000) | N85: Adamawa | O85: 4000 | P85: selected_food_table_Feb_25.xlsx
A86: Mar-2025 | B86: Dried fish, Bonga | C86: Dried fish, Bonga | D86: New (2025) | F86: 6160.0213 | G86: 6493.7843 | H86: 5.4182121 | J86: Ebonyi (10004.01) | K86: Ebonyi | L86: 10004.01 | M86: Osun (4420) | N86: Osun | O86: 4420 | P86: selected_food_table_Mar_25.xlsx
A87: Apr-2025 | B87: Dried fish, Bonga | C87: Dried fish, Bonga | D87: New (2025) | F87: 6493.7843 | G87: 6657.7428 | H87: 2.5248521 | J87: Ebonyi (10000) | K87: Ebonyi | L87: 10000 | M87: Osun (4500) | N87: Osun | O87: 4500 | P87: selected_food_table_Apr25.xlsx
A88: Nov-2024 | B88: Garri Yellow | C88: Gari yellow,sold loose | D88: Confirmed | E88: 581.09198 | F88: 1266.315 | G88: 1311.0287 | H88: 3.531011 | I88: 125.61466 | J88: Gombe (1575) | K88: Gombe | L88: 1575 | M88: Kogi (1100.03) | N88: Kogi | O88: 1100.03 | P88: selected_food_Nov_2024.xlsx
A89: Dec-2024 | B89: Garri Yellow | C89: Gari yellow,sold loose | D89: Confirmed | E89: 598.75055 | F89: 1311.0287 | G89: 1296.9267 | H89: -1.0756402 | I89: 116.60552 | J89: Gombe (1720) | K89: Gombe | L89: 1720 | M89: Kogi (1000.03) | N89: Kogi | O89: 1000.03 | P89: selected_food_Dec_2024.xlsx
A90: Jan-2025 | B90: Garri Yellow | C90: Garri Yellow | D90: Confirmed | E90: 624.21266 | F90: 1296.9267 | G90: 1358.9584 | H90: 4.7829754 | I90: 117.7076 | J90: Gombe (1692.31) | K90: Gombe | L90: 1692.31 | M90: Benue (980.24) | N90: Benue | O90: 980.24 | P90: Selected_food_table_Jan25.xlsx
A91: Feb-2025 | B91: Garri Yellow | C91: Garri Yellow | D91: Confirmed | E91: 753.56405 | F91: 1358.9584 | G91: 1378.1547 | H91: 1.4125736 | I91: 82.88488 | J91: Kebbi (1744.39) | K91: Kebbi | L91: 1744.39 | M91: Ekiti (961.54) | N91: Ekiti | O91: 961.54 | P91: selected_food_table_Feb_25.xlsx
A92: Mar-2025 | B92: Garri Yellow | C92: Garri Yellow | D92: Confirmed | E92: 804.01182 | F92: 1378.1547 | G92: 1456.6513 | H92: 5.6957726 | I92: 81.172867 | J92: Katsina (1903.28) | K92: Katsina | L92: 1903.28 | M92: Oyo (1152.77) | N92: Oyo | O92: 1152.77 | P92: selected_food_table_Mar_25.xlsx
A93: Apr-2025 | B93: Garri Yellow | C93: Garri Yellow | D93: Confirmed | E93: 909.76592 | F93: 1456.6513 | G93: 1422.3398 | H93: -2.3554998 | I93: 56.341298 | J93: Yobe (2060) | K93: Yobe | L93: 2060 | M93: Oyo (1100) | N93: Oyo | O93: 1100 | P93: selected_food_table_Apr25.xlsx
A94: Nov-2024 | B94: Garri white | C94: Gari white,sold loose | D94: Confirmed | E94: 548.95099 | F94: 1198.0472 | G94: 1205.3886 | H94: 0.61278118 | I94: 119.58037 | J94: Gombe (1550) | K94: Gombe | L94: 1550 | M94: Kogi (1000.04) | N94: Kogi | O94: 1000.04 | P94: selected_food_Nov_2024.xlsx
A95: Dec-2024 | B95: Garri white | C95: Gari white,sold loose | D95: Confirmed | E95: 568.71977 | F95: 1205.3886 | G95: 1184.7662 | H95: -1.7108511 | I95: 108.32161 | J95: Gombe (1500) | K95: Gombe | L95: 1500 | M95: Kogi (800.1) | N95: Kogi | O95: 800.1 | P95: selected_food_Dec_2024.xlsx
A96: Jan-2025 | B96: Garri white | C96: Garri white | D96: Confirmed | E96: 600.6872 | F96: 1184.7662 | G96: 1267.6349 | H96: 6.9945192 | I96: 111.03078 | J96: Abuja (1662.11) | K96: Abuja | L96: 1662.11 | M96: Oyo (909.09) | N96: Oyo | O96: 909.09 | P96: Selected_food_table_Jan25.xlsx
A97: Feb-2025 | B97: Garri white | C97: Garri white | D97: Confirmed | E97: 723.44894 | F97: 1267.6349 | G97: 1277.2471 | H97: 0.75827745 | I97: 76.549718 | J97: Kebbi (1693.78) | K97: Kebbi | L97: 1693.78 | M97: Ogun (923.61) | N97: Ogun | O97: 923.61 | P97: selected_food_table_Feb_25.xlsx
A98: Mar-2025 | B98: Garri white | C98: Garri white | D98: Confirmed | E98: 749.89277 | F98: 1277.2471 | G98: 1362.9593 | H98: 6.710702 | I98: 81.753895 | J98: Abuja (1901.33) | K98: Abuja | L98: 1901.33 | M98: Ondo (950) | N98: Ondo | O98: 950 | P98: selected_food_table_Mar_25.xlsx
A99: Apr-2025 | B99: Garri white | C99: Garri white | D99: Confirmed | E99: 851.80859 | F99: 1362.9593 | G99: 1345.0979 | H99: -1.3104914 | I99: 57.910811 | J99: Abuja (1902) | K99: Abuja | L99: 1902 | M99: Ondo (1000) | N99: Ondo | O99: 1000 | P99: selected_food_table_Apr25.xlsx
A100: Jan-2025 | B100: Ginger, fresh | C100: Ginger, fresh | D100: New (2025) | G100: 4206.7995 | J100: Oyo (5000) | K100: Oyo | L100: 5000 | M100: Katsina (2550) | N100: Katsina | O100: 2550 | P100: Selected_food_table_Jan25.xlsx
A101: Feb-2025 | B101: Ginger, fresh | C101: Ginger, fresh | D101: New (2025) | F101: 4206.7995 | G101: 4371.8969 | H101: 3.9245368 | J101: Rivers (5300) | K101: Rivers | L101: 5300 | M101: Katsina (2650) | N101: Katsina | O101: 2650 | P101: selected_food_table_Feb_25.xlsx
A102: Mar-2025 | B102: Ginger, fresh | C102: Ginger, fresh | D102: New (2025) | F102: 4371.8969 | G102: 4600.2308 | H102: 5.2227643 | J102: Ebonyi (6079.7) | K102: Ebonyi | L102: 6079.7 | M102: Katsina (3044.38) | N102: Katsina | O102: 3044.38 | P102: selected_food_table_Mar_25.xlsx
A103: Apr-2025 | B103: Ginger, fresh | C103: Ginger, fresh | D103: New (2025) | F103: 4600.2308 | G103: 4970.6588 | H103: 8.0523791 | J103: Ebonyi (6413.27) | K103: Ebonyi | L103: 6413.27 | M103: Adamawa (3800) | N103: Adamawa | O103: 3800 | P103: selected_food_table_Apr25.xlsx
A104: Jan-2025 | B104: Goat Meat Bone in | C104: Goat Meat Bone in | D104: New (2025) | G104: 6202.3575 | J104: Akwa Ibom (8687.5) | K104: Akwa Ibom | L104: 8687.5 | M104: Kogi (3925) | N104: Kogi | O104: 3925 | P104: Selected_food_table_Jan25.xlsx
A105: Feb-2025 | B105: Goat Meat Bone in | C105: Goat Meat Bone in | D105: New (2025) | F105: 6202.3575 | G105: 6298.8934 | H105: 1.5564387 | J105: Akwa Ibom (9500) | K105: Akwa Ibom | L105: 9500 | M105: Kogi (3800) | N105: Kogi | O105: 3800 | P105: selected_food_table_Feb_25.xlsx
A106: Mar-2025 | B106: Goat Meat Bone in | C106: Goat Meat Bone in | D106: New (2025) | F106: 6298.8934 | G106: 6892.4623 | H106: 9.4233838 | J106: Akwa Ibom (10340) | K106: Akwa Ibom | L106: 10340 | M106: Kogi (3850) | N106: Kogi | O106: 3850 | P106: selected_food_table_Mar_25.xlsx
A107: Apr-2025 | B107: Goat Meat Bone in | C107: Goat Meat Bone in | D107: New (2025) | F107: 6892.4623 | G107: 6708.4528 | H107: -2.6697214 | J107: Imo (9200) | K107: Imo | L107: 9200 | M107: Kogi (4000) | N107: Kogi | O107: 4000 | P107: selected_food_table_Apr25.xlsx
A108: Nov-2024 | B108: Groundnut oil, 75cl | C108: Groundnut oil: 1 bottle, specify bottle | D108: Likely | E108: 1738.9639 | F108: 2928.9168 | G108: 3165.3812 | H108: 8.0734425 | I108: 82.026853 | J108: Ekiti (4100) | K108: Ekiti | L108: 4100 | M108: Adamawa (2100) | N108: Adamawa | O108: 2100 | P108: selected_food_Nov_2024.xlsx
A109: Dec-2024 | B109: Groundnut oil, 75cl | C109: Groundnut oil: 1 bottle, specify bottle | D109: Likely | E109: 1806.953 | F109: 3165.3812 | G109: 3328.1693 | H109: 5.1427648 | I109: 84.186821 | J109: Osun (4133.33) | K109: Osun | L109: 4133.33 | M109: Niger (2282.59) | N109: Niger | O109: 2282.59 | P109: selected_food_Dec_2024.xlsx
A110: Jan-2025 | B110: Groundnut oil, 75cl | C110: Groundnut oil, 75cl | D110: Likely | G110: 2939.7346 | J110: Ogun (3900) | K110: Ogun | L110: 3900 | M110: Adamawa (2000) | N110: Adamawa | O110: 2000 | P110: Selected_food_table_Jan25.xlsx
A111: Feb-2025 | B111: Groundnut oil, 75cl | C111: Groundnut oil, 75cl | D111: Likely | F111: 2939.7346 | G111: 3039.8295 | H111: 3.4048939 | J111: Ogun (3900) | K111: Ogun | L111: 3900 | M111: Abuja (2250) | N111: Abuja | O111: 2250 | P111: selected_food_table_Feb_25.xlsx
A112: Mar-2025 | B112: Groundnut oil, 75cl | C112: Groundnut oil, 75cl | D112: Likely | F112: 3039.8295 | G112: 3218.8178 | H112: 5.8881052 | J112: Ekiti (4209.71) | K112: Ekiti | L112: 4209.71 | M112: Ebonyi (2394.41) | N112: Ebonyi | O112: 2394.41 | P112: selected_food_table_Mar_25.xlsx
A113: Apr-2025 | B113: Groundnut oil, 75cl | C113: Groundnut oil, 75cl | D113: Likely | F113: 3218.8178 | G113: 3250.3191 | H113: 0.97866058 | J113: Ekiti (4200) | K113: Ekiti | L113: 4200 | M113: Abia (2335.05) | N113: Abia | O113: 2335.05 | P113: selected_food_table_Apr25.xlsx
A114: Jan-2025 | B114: Groundnuts, roasted,75cl bottle | C114: Groundnuts, roasted,75cl bottle | D114: New (2025) | G114: 2387.7568 | J114: Bayelsa (3125) | K114: Bayelsa | L114: 3125 | M114: Kano (1806.47) | N114: Kano | O114: 1806.47 | P114: Selected_food_table_Jan25.xlsx
A115: Feb-2025 | B115: Groundnuts, roasted,75cl bottle | C115: Groundnuts, roasted,75cl bottle | D115: New (2025) | F115: 2387.7568 | G115: 2392.4711 | H115: 0.19743431 | J115: Bayelsa (3148.21) | K115: Bayelsa | L115: 3148.21 | M115: Osun (1900) | N115: Osun | O115: 1900 | P115: selected_food_table_Feb_25.xlsx
A116: Mar-2025 | B116: Groundnuts, roasted,75cl bottle | C116: Groundnuts, roasted,75cl bottle | D116: New (2025) | F116: 2392.4711 | G116: 2487.6765 | H116: 3.9793781 | J116: Zamfara (3235.2) | K116: Zamfara | L116: 3235.2 | M116: Kwara (2000) | N116: Kwara | O116: 2000 | P116: selected_food_table_Mar_25.xlsx
A117: Apr-2025 | B117: Groundnuts, roasted,75cl bottle | C117: Groundnuts, roasted,75cl bottle | D117: New (2025) | F117: 2487.6765 | G117: 2545.7164 | H117: 2.3330977 | J117: Bayelsa (3223.21) | K117: Bayelsa | L117: 3223.21 | M117: Yobe (2100) | N117: Yobe | O117: 2100 | P117: selected_food_table_Apr25.xlsx
A118: Nov-2024 | B118: Iced Sardine | C118: Iced Sardine | D118: Discontinued | E118: 2222.9853 | F118: 3706.8927 | G118: 3875.6589 | H118: 4.5527696 | I118: 74.344787 | J118: Gombe (5308.98) | K118: Gombe | L118: 5308.98 | M118: Niger (2562.63) | N118: Niger | O118: 2562.63 | P118: selected_food_Nov_2024.xlsx
A119: Dec-2024 | B119: Iced Sardine | C119: Iced Sardine | D119: Discontinued | E119: 2303.964 | F119: 3875.6589 | G119: 4014.2349 | H119: 3.5755458 | I119: 74.231669 | J119: Gombe (5850.39) | K119: Gombe | L119: 5850.39 | M119: Niger (2565.63) | N119: Niger | O119: 2565.63 | P119: selected_food_Dec_2024.xlsx
A120: Nov-2024 | B120: Irish Potatoe | C120: Irish potato | D120: Confirmed | E120: 872.63198 | F120: 1733.4783 | G120: 1778.9605 | H120: 2.6237522 | I120: 103.86148 | J120: Kogi (2839.31) | K120: Kogi | L120: 2839.31 | M120: Bauchi (1075.42) | N120: Bauchi | O120: 1075.42 | P120: selected_food_Nov_2024.xlsx
A121: Dec-2024 | B121: Irish Potatoe | C121: Irish potato | D121: Confirmed | E121: 1006.3627 | F121: 1778.9605 | G121: 1818.2876 | H121: 2.2106818 | I121: 80.679153 | J121: Kogi (2840.23) | K121: Kogi | L121: 2840.23 | M121: Yobe (1038.46) | N121: Yobe | O121: 1038.46 | P121: selected_food_Dec_2024.xlsx
A122: Jan-2025 | B122: Irish Potatoe | C122: Irish Potatoe | D122: Confirmed | E122: 1051.7684 | F122: 1818.2876 | G122: 1790.9109 | H122: -1.505634 | I122: 70.276157 | J122: Oyo (2687.5) | K122: Oyo | L122: 2687.5 | M122: Abuja (972.45) | N122: Abuja | O122: 972.45 | P122: Selected_food_table_Jan25.xlsx
A123: Feb-2025 | B123: Irish Potatoe | C123: Irish Potatoe | D123: Confirmed | E123: 1130.6297 | F123: 1790.9109 | G123: 1756.4073 | H123: -1.9265956 | I123: 55.347702 | J123: Anambra (2782.21) | K123: Anambra | L123: 2782.21 | M123: Abuja (931.78) | N123: Abuja | O123: 931.78 | P123: selected_food_table_Feb_25.xlsx
A124: Mar-2025 | B124: Irish Potatoe | C124: Irish Potatoe | D124: Confirmed | E124: 1254.4506 | F124: 1756.4073 | G124: 1881.7563 | H124: 7.136671 | I124: 50.006412 | J124: Anambra (3021.19) | K124: Anambra | L124: 3021.19 | M124: Abuja (1098.24) | N124: Abuja | O124: 1098.24 | P124: selected_food_table_Mar_25.xlsx
...

Sheet Item Summary
A1: Standardized Item | B1: Match Confidence | C1: Months Covered | D1: Avg Price Nov-2024 | E1: Avg Price Dec-2024 | F1: Avg Price Jan-2025 | G1: Avg Price Feb-2025 | H1: Avg Price Mar-2025 | I1: Avg Price Apr-2025 | J1: Avg MoM % | K1: Avg YoY % | L1: Latest Price
A2: Agric hen eggs | B2: =IFERROR(INDEX('Standardized Data'!$D$2:$D$255,MATCH($A2,'Standardized Data'!$B$2:$B$255,0)),"") -> Confirmed | C2: =COUNTIF('Standardized Data'!$B$2:$B$255,$A2) -> 6 | D2: =IF(SUMIFS('Standardized Data'!$G$2:$G$255,'Standardized Data'!$B$2:$B$255,$A2,'Standardized Data'!$A$2:$A$255,"Nov-2024")=0,"",SUMIFS('Standardized Data'!$G$2:$G$255,'Standardized Data'!$B$2:$B$255,$A2,'Standardized Data'!$A$2:$A$255,"Nov-2024")) -> 247.2591 | E2: =IF(SUMIFS('Standardized Data'!$G$2:$G$255,'Standardized Data'!$B$2:$B$255,$A2,'Standardized Data'!$A$2:$A$255,"Dec-2024")=0,"",SUMIFS('Standardized Data'!$G$2:$G$255,'Standardized Data'!$B$2:$B$255,$A2,'Standardized Data'!$A$2:$A$255,"Dec-2024")) -> 252.1655 | F2: =IF(SUMIFS('Standardized Data'!$G$2:$G$255,'Standardized Data'!$B$2:$B$255,$A2,'Standardized Data'!$A$2:$A$255,"Jan-2025")=0,"",SUMIFS('Standardized Data'!$G$2:$G$255,'Standardized Data'!$B$2:$B$255,$A2,'Standardized Data'!$A$2:$A$255,"Jan-2025")) -> 248.04139 | G2: =IF(SUMIFS('Standardized Data'!$G$2:$G$255,'Standardized Data'!$B$2:$B$255,$A2,'Standardized Data'!$A$2:$A$255,"Feb-2025")=0,"",SUMIFS('Standardized Data'!$G$2:$G$255,'Standardized Data'!$B$2:$B$255,$A2,'Standardized Data'!$A$2:$A$255,"Feb-2025")) -> 251.94052 | H2: =IF(SUMIFS('Standardized Data'!$G$2:$G$255,'Standardized Data'!$B$2:$B$255,$A2,'Standardized Data'!$A$2:$A$255,"Mar-2025")=0,"",SUMIFS('Standardized Data'!$G$2:$G$255,'Standardized Data'!$B$2:$B$255,$A2,'Standardized Data'!$A$2:$A$255,"Mar-2025")) -> 261.18235 | I2: =IF(SUMIFS('Standardized Data'!$G$2:$G$255,'Standardized Data'!$B$2:$B$255,$A2,'Standardized Data'!$A$2:$A$255,"Apr-2025")=0,"",SUMIFS('Standardized Data'!$G$2:$G$255,'Standardized Data'!$B$2:$B$255,$A2,'Standardized Data'!$A$2:$A$255,"Apr-2025")) -> 259.31615 | J2: =IFERROR(AVERAGEIFS('Standardized Data'!$H$2:$H$255,'Standardized Data'!$B$2:$B$255,$A2),"") -> 1.6317499 | K2: =IFERROR(AVERAGEIFS('Standardized Data'!$I$2:$I$255,'Standardized Data'!$B$2:$B$255,$A2),"") -> 99.36031 | L2: =IF(I2<>"",I2,IF(H2<>"",H2,IF(G2<>"",G2,IF(F2<>"",F2,IF(E2<>"",E2,IF(D2<>"",D2,"")))))) -> 259.31615
A3: Agric hen eggs, (a Crate of 30 pieces) | B3: =IFERROR(INDEX('Standardized Data'!$D$2:$D$255,MATCH($A3,'Standardized Data'!$B$2:$B$255,0)),"") -> Likely | C3: =COUNTIF('Standardized Data'!$B$2:$B$255,$A3) -> 6 | D3: =IF(SUMIFS('Standardized Data'!$G$2:$G$255,'Standardized Data'!$B$2:$B$255,$A3,'Standardized Data'!$A$2:$A$255,"Nov-2024")=0,"",SUMIFS('Standardized Data'!$G$2:$G$255,'Standardized Data'!$B$2:$B$255,$A3,'Standardized Data'!$A$2:$A$255,"Nov-2024")) -> 2833.973 | E3: =IF(SUMIFS('Standardized Data'!$G$2:$G$255,'Standardized Data'!$B$2:$B$255,$A3,'Standardized Data'!$A$2:$A$255,"Dec-2024")=0,"",SUMIFS('Standardized Data'!$G$2:$G$255,'Standardized Data'!$B$2:$B$255,$A3,'Standardized Data'!$A$2:$A$255,"Dec-2024")) -> 2866.9151 | F3: =IF(SUMIFS('Standardized Data'!$G$2:$G$255,'Standardized Data'!$B$2:$B$255,$A3,'Standardized Data'!$A$2:$A$255,"Jan-2025")=0,"",SUMIFS('Standardized Data'!$G$2:$G$255,'Standardized Data'!$B$2:$B$255,$A3,'Standardized Data'!$A$2:$A$255,"Jan-2025")) -> 5878.1406 | G3: =IF(SUMIFS('Standardized Data'!$G$2:$G$255,'Standardized Data'!$B$2:$B$255,$A3,'Standardized Data'!$A$2:$A$255,"Feb-2025")=0,"",SUMIFS('Standardized Data'!$G$2:$G$255,'Standardized Data'!$B$2:$B$255,$A3,'Standardized Data'!$A$2:$A$255,"Feb-2025")) -> 5976.1159 | H3: =IF(SUMIFS('Standardized Data'!$G$2:$G$255,'Standardized Data'!$B$2:$B$255,$A3,'Standardized Data'!$A$2:$A$255,"Mar-2025")=0,"",SUMIFS('Standardized Data'!$G$2:$G$255,'Standardized Data'!$B$2:$B$255,$A3,'Standardized Data'!$A$2:$A$255,"Mar-2025")) -> 7670.5592 | I3: =IF(SUMIFS('Standardized Data'!$G$2:$G$255,'Standardized Data'!$B$2:$B$255,$A3,'Standardized Data'!$A$2:$A$255,"Apr-2025")=0,"",SUMIFS('Standardized Data'!$G$2:$G$255,'Standardized Data'!$B$2:$B$255,$A3,'Standardized Data'!$A$2:$A$255,"Apr-2025")) -> 6150.1781 | J3: =IFERROR(AVERAGEIFS('Standardized Data'!$H$2:$H$255,'Standardized Data'!$B$2:$B$255,$A3),"") -> 3.4878852 | K3: =IFERROR(AVERAGEIFS('Standardized Data'!$I$2:$I$255,'Standardized Data'!$B$2:$B$255,$A3),"") -> 132.09737 | L3: =IF(I3<>"",I3,IF(H3<>"",H3,IF(G3<>"",G3,IF(F3<>"",F3,IF(E3<>"",E3,IF(D3<>"",D3,"")))))) -> 6150.1781
A4: Beans Brown | B4: =IFERROR(INDEX('Standardized Data'!$D$2:$D$255,MATCH($A4,'Standardized Data'!$B$2:$B$255,0)),"") -> Confirmed | C4: =COUNTIF('Standardized Data'!$B$2:$B$255,$A4) -> 6 | D4: =IF(SUMIFS('Standardized Data'!$G$2:$G$255,'Standardized Data'!$B$2:$B$255,$A4,'Standardized Data'!$A$2:$A$255,"Nov-2024")=0,"",SUMIFS('Standardized Data'!$G$2:$G$255,'Standardized Data'!$B$2:$B$255,$A4,'Standardized Data'!$A$2:$A$255,"Nov-2024")) -> 2720.9608 | E4: =IF(SUMIFS('Standardized Data'!$G$2:$G$255,'Standardized Data'!$B$2:$B$255,$A4,'Standardized Data'!$A$2:$A$255,"Dec-2024")=0,"",SUMIFS('Standardized Data'!$G$2:$G$255,'Standardized Data'!$B$2:$B$255,$A4,'Standardized Data'!$A$2:$A$255,"Dec-2024")) -> 2501.3235 | F4: =IF(SUMIFS('Standardized Data'!$G$2:$G$255,'Standardized Data'!$B$2:$B$255,$A4,'Standardized Data'!$A$2:$A$255,"Jan-2025")=0,"",SUMIFS('Standardized Data'!$G$2:$G$255,'Standardized Data'!$B$2:$B$255,$A4,'Standardized Data'!$A$2:$A$255,"Jan-2025")) -> 2458.5333 | G4: =IF(SUMIFS('Standardized Data'!$G$2:$G$255,'Standardized Data'!$B$2:$B$255,$A4,'Standardized Data'!$A$2:$A$255,"Feb-2025")=0,"",SUMIFS('Standardized Data'!$G$2:$G$255,'Standardized Data'!$B$2:$B$255,$A4,'Standardized Data'!$A$2:$A$255,"Feb-2025")) -> 2465.9628 | H4: =IF(SUMIFS('Standardized Data'!$G$2:$G$255,'Standardized Data'!$B$2:$B$255,$A4,'Standardized Data'!$A$2:$A$255,"Mar-2025")=0,"",SUMIFS('Standardized Data'!$G$2:$G$255,'Standardized Data'!$B$2:$B$255,$A4,'Standardized Data'!$A$2:$A$255,"Mar-2025")) -> 2616.2636 | I4: =IF(SUMIFS('Standardized Data'!$G$2:$G$255,'Standardized Data'!$B$2:$B$255,$A4,'Standardized Data'!$A$2:$A$255,"Apr-2025")=0,"",SUMIFS('Standardized Data'!$G$2:$G$255,'Standardized Data'!$B$2:$B$255,$A4,'Standardized Data'!$A$2:$A$255,"Apr-2025")) -> 2429.3886 | J4: =IFERROR(AVERAGEIFS('Standardized Data'!$H$2:$H$255,'Standardized Data'!$B$2:$B$255,$A4),"") -> -2.2164959 | K4: =IFERROR(AVERAGEIFS('Standardized Data'!$I$2:$I$255,'Standardized Data'!$B$2:$B$255,$A4),"") -> 143.28973 | L4: =IF(I4<>"",I4,IF(H4<>"",H4,IF(G4<>"",G4,IF(F4<>"",F4,IF(E4<>"",E4,IF(D4<>"",D4,"")))))) -> 2429.3886
A5: Beans white | B5: =IFERROR(INDEX('Standardized Data'!$D$2:$D$255,MATCH($A5,'Standardized Data'!$B$2:$B$255,0)),"") -> Confirmed | C5: =COUNTIF('Standardized Data'!$B$2:$B$255,$A5) -> 6 | D5: =IF(SUMIFS('Standardized Data'!$G$2:$G$255,'Standardized Data'!$B$2:$B$255,$A5,'Standardized Data'!$A$2:$A$255,"Nov-2024")=0,"",SUMIFS('Standardized Data'!$G$2:$G$255,'Standardized Data'!$B$2:$B$255,$A5,'Standardized Data'!$A$2:$A$255,"Nov-2024")) -> 2546.7025 | E5: =IF(SUMIFS('Standardized Data'!$G$2:$G$255,'Standardized Data'!$B$2:$B$255,$A5,'Standardized Data'!$A$2:$A$255,"Dec-2024")=0,"",SUMIFS('Standardized Data'!$G$2:$G$255,'Standardized Data'!$B$2:$B$255,$A5,'Standardized Data'!$A$2:$A$255,"Dec-2024")) -> 2319.0422 | F5: =IF(SUMIFS('Standardized Data'!$G$2:$G$255,'Standardized Data'!$B$2:$B$255,$A5,'Standardized Data'!$A$2:$A$255,"Jan-2025")=0,"",SUMIFS('Standardized Data'!$G$2:$G$255,'Standardized Data'!$B$2:$B$255,$A5,'Standardized Data'!$A$2:$A$255,"Jan-2025")) -> 2123.853 | G5: =IF(SUMIFS('Standardized Data'!$G$2:$G$255,'Standardized Data'!$B$2:$B$255,$A5,'Standardized Data'!$A$2:$A$255,"Feb-2025")=0,"",SUMIFS('Standardized Data'!$G$2:$G$255,'Standardized Data'!$B$2:$B$255,$A5,'Standardized Data'!$A$2:$A$255,"Feb-2025")) -> 2114.3292 | H5: =IF(SUMIFS('Standardized Data'!$G$2:$G$255,'Standardized Data'!$B$2:$B$255,$A5,'Standardized Data'!$A$2:$A$255,"Mar-2025")=0,"",SUMIFS('Standardized Data'!$G$2:$G$255,'Standardized Data'!$B$2:$B$255,$A5,'Standardized Data'!$A$2:$A$255,"Mar-2025")) -> 2215.1071 | I5: =IF(SUMIFS('Standardized Data'!$G$2:$G$255,'Standardized Data'!$B$2:$B$255,$A5,'Standardized Data'!$A$2:$A$255,"Apr-2025")=0,"",SUMIFS('Standardized Data'!$G$2:$G$255,'Standardized Data'!$B$2:$B$255,$A5,'Standardized Data'!$A$2:$A$255,"Apr-2025")) -> 2097.3099 | J5: =IFERROR(AVERAGEIFS('Standardized Data'!$H$2:$H$255,'Standardized Data'!$B$2:$B$255,$A5),"") -> -3.4218097 | K5: =IFERROR(AVERAGEIFS('Standardized Data'!$I$2:$I$255,'Standardized Data'!$B$2:$B$255,$A5),"") -> 126.05759 | L5: =IF(I5<>"",I5,IF(H5<>"",H5,IF(G5<>"",G5,IF(F5<>"",F5,IF(E5<>"",E5,IF(D5<>"",D5,"")))))) -> 2097.3099
A6: Beef Bone in | B6: =IFERROR(INDEX('Standardized Data'!$D$2:$D$255,MATCH($A6,'Standardized Data'!$B$2:$B$255,0)),"") -> Discontinued | C6: =COUNTIF('Standardized Data'!$B$2:$B$255,$A6) -> 2 | D6: =IF(SUMIFS('Standardized Data'!$G$2:$G$255,'Standardized Data'!$B$2:$B$255,$A6,'Standardized Data'!$A$2:$A$255,"Nov-2024")=0,"",SUMIFS('Standardized Data'!$G$2:$G$255,'Standardized Data'!$B$2:$B$255,$A6,'Standardized Data'!$A$2:$A$255,"Nov-2024")) -> 5073.7358 | E6: =IF(SUMIFS('Standardized Data'!$G$2:$G$255,'Standardized Data'!$B$2:$B$255,$A6,'Standardized Data'!$A$2:$A$255,"Dec-2024")=0,"",SUMIFS('Standardized Data'!$G$2:$G$255,'Standardized Data'!$B$2:$B$255,$A6,'Standardized Data'!$A$2:$A$255,"Dec-2024")) -> 5153.1849 | F6: =IF(SUMIFS('Standardized Data'!$G$2:$G$255,'Standardized Data'!$B$2:$B$255,$A6,'Standardized Data'!$A$2:$A$255,"Jan-2025")=0,"",SUMIFS('Standardized Data'!$G$2:$G$255,'Standardized Data'!$B$2:$B$255,$A6,'Standardized Data'!$A$2:$A$255,"Jan-2025")) | G6: =IF(SUMIFS('Standardized Data'!$G$2:$G$255,'Standardized Data'!$B$2:$B$255,$A6,'Standardized Data'!$A$2:$A$255,"Feb-2025")=0,"",SUMIFS('Standardized Data'!$G$2:$G$255,'Standardized Data'!$B$2:$B$255,$A6,'Standardized Data'!$A$2:$A$255,"Feb-2025")) | H6: =IF(SUMIFS('Standardized Data'!$G$2:$G$255,'Standardized Data'!$B$2:$B$255,$A6,'Standardized Data'!$A$2:$A$255,"Mar-2025")=0,"",SUMIFS('Standardized Data'!$G$2:$G$255,'Standardized Data'!$B$2:$B$255,$A6,'Standardized Data'!$A$2:$A$255,"Mar-2025")) | I6: =IF(SUMIFS('Standardized Data'!$G$2:$G$255,'Standardized Data'!$B$2:$B$255,$A6,'Standardized Data'!$A$2:$A$255,"Apr-2025")=0,"",SUMIFS('Standardized Data'!$G$2:$G$255,'Standardized Data'!$B$2:$B$255,$A6,'Standardized Data'!$A$2:$A$255,"Apr-2025")) | J6: =IFERROR(AVERAGEIFS('Standardized Data'!$H$2:$H$255,'Standardized Data'!$B$2:$B$255,$A6),"") -> 2.4017255 | K6: =IFERROR(AVERAGEIFS('Standardized Data'!$I$2:$I$255,'Standardized Data'!$B$2:$B$255,$A6),"") -> 91.99809 | L6: =IF(I6<>"",I6,IF(H6<>"",H6,IF(G6<>"",G6,IF(F6<>"",F6,IF(E6<>"",E6,IF(D6<>"",D6,"")))))) -> 5153.1849
A7: Beef Boneless | B7: =IFERROR(INDEX('Standardized Data'!$D$2:$D$255,MATCH($A7,'Standardized Data'!$B$2:$B$255,0)),"") -> Confirmed | C7: =COUNTIF('Standardized Data'!$B$2:$B$255,$A7) -> 6 | D7: =IF(SUMIFS('Standardized Data'!$G$2:$G$255,'Standardized Data'!$B$2:$B$255,$A7,'Standardized Data'!$A$2:$A$255,"Nov-2024")=0,"",SUMIFS('Standardized Data'!$G$2:$G$255,'Standardized Data'!$B$2:$B$255,$A7,'Standardized Data'!$A$2:$A$255,"Nov-2024")) -> 6001.3163 | E7: =IF(SUMIFS('Standardized Data'!$G$2:$G$255,'Standardized Data'!$B$2:$B$255,$A7,'Standardized Data'!$A$2:$A$255,"Dec-2024")=0,"",SUMIFS('Standardized Data'!$G$2:$G$255,'Standardized Data'!$B$2:$B$255,$A7,'Standardized Data'!$A$2:$A$255,"Dec-2024")) -> 6150.1829 | F7: =IF(SUMIFS('Standardized Data'!$G$2:$G$255,'Standardized Data'!$B$2:$B$255,$A7,'Standardized Data'!$A$2:$A$255,"Jan-2025")=0,"",SUMIFS('Standardized Data'!$G$2:$G$255,'Standardized Data'!$B$2:$B$255,$A7,'Standardized Data'!$A$2:$A$255,"Jan-2025")) -> 6122.5683 | G7: =IF(SUMIFS('Standardized Data'!$G$2:$G$255,'Standardized Data'!$B$2:$B$255,$A7,'Standardized Data'!$A$2:$A$255,"Feb-2025")=0,"",SUMIFS('Standardized Data'!$G$2:$G$255,'Standardized Data'!$B$2:$B$255,$A7,'Standardized Data'!$A$2:$A$255,"Feb-2025")) -> 6269.4588 | H7: =IF(SUMIFS('Standardized Data'!$G$2:$G$255,'Standardized Data'!$B$2:$B$255,$A7,'Standardized Data'!$A$2:$A$255,"Mar-2025")=0,"",SUMIFS('Standardized Data'!$G$2:$G$255,'Standardized Data'!$B$2:$B$255,$A7,'Standardized Data'!$A$2:$A$255,"Mar-2025")) -> 6523.501 | I7: =IF(SUMIFS('Standardized Data'!$G$2:$G$255,'Standardized Data'!$B$2:$B$255,$A7,'Standardized Data'!$A$2:$A$255,"Apr-2025")=0,"",SUMIFS('Standardized Data'!$G$2:$G$255,'Standardized Data'!$B$2:$B$255,$A7,'Standardized Data'!$A$2:$A$255,"Apr-2025")) -> 6544.5369 | J7: =IFERROR(AVERAGEIFS('Standardized Data'!$H$2:$H$255,'Standardized Data'!$B$2:$B$255,$A7),"") -> 1.8736114 | K7: =IFERROR(AVERAGEIFS('Standardized Data'!$I$2:$I$255,'Standardized Data'!$B$2:$B$255,$A7),"") -> 73.336427 | L7: =IF(I7<>"",I7,IF(H7<>"",H7,IF(G7<>"",G7,IF(F7<>"",F7,IF(E7<>"",E7,IF(D7<>"",D7,"")))))) -> 6544.5369
A8: Bread (sliced), 450g | B8: =IFERROR(INDEX('Standardized Data'!$D$2:$D$255,MATCH($A8,'Standardized Data'!$B$2:$B$255,0)),"") -> Likely | C8: =COUNTIF('Standardized Data'!$B$2:$B$255,$A8) -> 6 | D8: =IF(SUMIFS('Standardized Data'!$G$2:$G$255,'Standardized Data'!$B$2:$B$255,$A8,'Standardized Data'!$A$2:$A$255,"Nov-2024")=0,"",SUMIFS('Standardized Data'!$G$2:$G$255,'Standardized Data'!$B$2:$B$255,$A8,'Standardized Data'!$A$2:$A$255,"Nov-2024")) -> 1588.0267 | E8: =IF(SUMIFS('Standardized Data'!$G$2:$G$255,'Standardized Data'!$B$2:$B$255,$A8,'Standardized Data'!$A$2:$A$255,"Dec-2024")=0,"",SUMIFS('Standardized Data'!$G$2:$G$255,'Standardized Data'!$B$2:$B$255,$A8,'Standardized Data'!$A$2:$A$255,"Dec-2024")) -> 1610.8262 | F8: =IF(SUMIFS('Standardized Data'!$G$2:$G$255,'Standardized Data'!$B$2:$B$255,$A8,'Standardized Data'!$A$2:$A$255,"Jan-2025")=0,"",SUMIFS('Standardized Data'!$G$2:$G$255,'Standardized Data'!$B$2:$B$255,$A8,'Standardized Data'!$A$2:$A$255,"Jan-2025")) -> 1604.7842 | G8: =IF(SUMIFS('Standardized Data'!$G$2:$G$255,'Standardized Data'!$B$2:$B$255,$A8,'Standardized Data'!$A$2:$A$255,"Feb-2025")=0,"",SUMIFS('Standardized Data'!$G$2:$G$255,'Standardized Data'!$B$2:$B$255,$A8,'Standardized Data'!$A$2:$A$255,"Feb-2025")) -> 1633.1854 | H8: =IF(SUMIFS('Standardized Data'!$G$2:$G$255,'Standardized Data'!$B$2:$B$255,$A8,'Standardized Data'!$A$2:$A$255,"Mar-2025")=0,"",SUMIFS('Standardized Data'!$G$2:$G$255,'Standardized Data'!$B$2:$B$255,$A8,'Standardized Data'!$A$2:$A$255,"Mar-2025")) -> 1680.1747 | I8: =IF(SUMIFS('Standardized Data'!$G$2:$G$255,'Standardized Data'!$B$2:$B$255,$A8,'Standardized Data'!$A$2:$A$255,"Apr-2025")=0,"",SUMIFS('Standardized Data'!$G$2:$G$255,'Standardized Data'!$B$2:$B$255,$A8,'Standardized Data'!$A$2:$A$255,"Apr-2025")) -> 1688.3998 | J8: =IFERROR(AVERAGEIFS('Standardized Data'!$H$2:$H$255,'Standardized Data'!$B$2:$B$255,$A8),"") -> 1.8018964 | K8: =IFERROR(AVERAGEIFS('Standardized Data'!$I$2:$I$255,'Standardized Data'!$B$2:$B$255,$A8),"") -> 91.676148 | L8: =IF(I8<>"",I8,IF(H8<>"",H8,IF(G8<>"",G8,IF(F8<>"",F8,IF(E8<>"",E8,IF(D8<>"",D8,"")))))) -> 1688.3998
A9: Bread (unsliced), 450g | B9: =IFERROR(INDEX('Standardized Data'!$D$2:$D$255,MATCH($A9,'Standardized Data'!$B$2:$B$255,0)),"") -> Likely | C9: =COUNTIF('Standardized Data'!$B$2:$B$255,$A9) -> 6 | D9: =IF(SUMIFS('Standardized Data'!$G$2:$G$255,'Standardized Data'!$B$2:$B$255,$A9,'Standardized Data'!$A$2:$A$255,"Nov-2024")=0,"",SUMIFS('Standardized Data'!$G$2:$G$255,'Standardized Data'!$B$2:$B$255,$A9,'Standardized Data'!$A$2:$A$255,"Nov-2024")) -> 1486.2466 | E9: =IF(SUMIFS('Standardized Data'!$G$2:$G$255,'Standardized Data'!$B$2:$B$255,$A9,'Standardized Data'!$A$2:$A$255,"Dec-2024")=0,"",SUMIFS('Standardized Data'!$G$2:$G$255,'Standardized Data'!$B$2:$B$255,$A9,'Standardized Data'!$A$2:$A$255,"Dec-2024")) -> 1512.1275 | F9: =IF(SUMIFS('Standardized Data'!$G$2:$G$255,'Standardized Data'!$B$2:$B$255,$A9,'Standardized Data'!$A$2:$A$255,"Jan-2025")=0,"",SUMIFS('Standardized Data'!$G$2:$G$255,'Standardized Data'!$B$2:$B$255,$A9,'Standardized Data'!$A$2:$A$255,"Jan-2025")) -> 1452.983 | G9: =IF(SUMIFS('Standardized Data'!$G$2:$G$255,'Standardized Data'!$B$2:$B$255,$A9,'Standardized Data'!$A$2:$A$255,"Feb-2025")=0,"",SUMIFS('Standardized Data'!$G$2:$G$255,'Standardized Data'!$B$2:$B$255,$A9,'Standardized Data'!$A$2:$A$255,"Feb-2025")) -> 1497.4272 | H9: =IF(SUMIFS('Standardized Data'!$G$2:$G$255,'Standardized Data'!$B$2:$B$255,$A9,'Standardized Data'!$A$2:$A$255,"Mar-2025")=0,"",SUMIFS('Standardized Data'!$G$2:$G$255,'Standardized Data'!$B$2:$B$255,$A9,'Standardized Data'!$A$2:$A$255,"Mar-2025")) -> 1561.2438 | I9: =IF(SUMIFS('Standardized Data'!$G$2:$G$255,'Standardized Data'!$B$2:$B$255,$A9,'Standardized Data'!$A$2:$A$255,"Apr-2025")=0,"",SUMIFS('Standardized Data'!$G$2:$G$255,'Standardized Data'!$B$2:$B$255,$A9,'Standardized Data'!$A$2:$A$255,"Apr-2025")) -> 1547.5179 | J9: =IFERROR(AVERAGEIFS('Standardized Data'!$H$2:$H$255,'Standardized Data'!$B$2:$B$255,$A9),"") -> 2.0739804 | K9: =IFERROR(AVERAGEIFS('Standardized Data'!$I$2:$I$255,'Standardized Data'!$B$2:$B$255,$A9),"") -> 86.133272 | L9: =IF(I9<>"",I9,IF(H9<>"",H9,IF(G9<>"",G9,IF(F9<>"",F9,IF(E9<>"",E9,IF(D9<>"",D9,"")))))) -> 1547.5179
A10: Carrots, fresh | B10: =IFERROR(INDEX('Standardized Data'!$D$2:$D$255,MATCH($A10,'Standardized Data'!$B$2:$B$255,0)),"") -> New (2025) | C10: =COUNTIF('Standardized Data'!$B$2:$B$255,$A10) -> 4 | D10: =IF(SUMIFS('Standardized Data'!$G$2:$G$255,'Standardized Data'!$B$2:$B$255,$A10,'Standardized Data'!$A$2:$A$255,"Nov-2024")=0,"",SUMIFS('Standardized Data'!$G$2:$G$255,'Standardized Data'!$B$2:$B$255,$A10,'Standardized Data'!$A$2:$A$255,"Nov-2024")) | E10: =IF(SUMIFS('Standardized Data'!$G$2:$G$255,'Standardized Data'!$B$2:$B$255,$A10,'Standardized Data'!$A$2:$A$255,"Dec-2024")=0,"",SUMIFS('Standardized Data'!$G$2:$G$255,'Standardized Data'!$B$2:$B$255,$A10,'Standardized Data'!$A$2:$A$255,"Dec-2024")) | F10: =IF(SUMIFS('Standardized Data'!$G$2:$G$255,'Standardized Data'!$B$2:$B$255,$A10,'Standardized Data'!$A$2:$A$255,"Jan-2025")=0,"",SUMIFS('Standardized Data'!$G$2:$G$255,'Standardized Data'!$B$2:$B$255,$A10,'Standardized Data'!$A$2:$A$255,"Jan-2025")) -> 1787.1615 | G10: =IF(SUMIFS('Standardized Data'!$G$2:$G$255,'Standardized Data'!$B$2:$B$255,$A10,'Standardized Data'!$A$2:$A$255,"Feb-2025")=0,"",SUMIFS('Standardized Data'!$G$2:$G$255,'Standardized Data'!$B$2:$B$255,$A10,'Standardized Data'!$A$2:$A$255,"Feb-2025")) -> 1838.5928 | H10: =IF(SUMIFS('Standardized Data'!$G$2:$G$255,'Standardized Data'!$B$2:$B$255,$A10,'Standardized Data'!$A$2:$A$255,"Mar-2025")=0,"",SUMIFS('Standardized Data'!$G$2:$G$255,'Standardized Data'!$B$2:$B$255,$A10,'Standardized Data'!$A$2:$A$255,"Mar-2025")) -> 1947.0497 | I10: =IF(SUMIFS('Standardized Data'!$G$2:$G$255,'Standardized Data'!$B$2:$B$255,$A10,'Standardized Data'!$A$2:$A$255,"Apr-2025")=0,"",SUMIFS('Standardized Data'!$G$2:$G$255,'Standardized Data'!$B$2:$B$255,$A10,'Standardized Data'!$A$2:$A$255,"Apr-2025")) -> 1931.3179 | J10: =IFERROR(AVERAGEIFS('Standardized Data'!$H$2:$H$255,'Standardized Data'!$B$2:$B$255,$A10),"") -> 2.6562493 | K10: =IFERROR(AVERAGEIFS('Standardized Data'!$I$2:$I$255,'Standardized Data'!$B$2:$B$255,$A10),"") | L10: =IF(I10<>"",I10,IF(H10<>"",H10,IF(G10<>"",G10,IF(F10<>"",F10,IF(E10<>"",E10,IF(D10<>"",D10,"")))))) -> 1931.3179
A11: Cat fresh fish | B11: =IFERROR(INDEX('Standardized Data'!$D$2:$D$255,MATCH($A11,'Standardized Data'!$B$2:$B$255,0)),"") -> Confirmed | C11: =COUNTIF('Standardized Data'!$B$2:$B$255,$A11) -> 6 | D11: =IF(SUMIFS('Standardized Data'!$G$2:$G$255,'Standardized Data'!$B$2:$B$255,$A11,'Standardized Data'!$A$2:$A$255,"Nov-2024")=0,"",SUMIFS('Standardized Data'!$G$2:$G$255,'Standardized Data'!$B$2:$B$255,$A11,'Standardized Data'!$A$2:$A$255,"Nov-2024")) -> 4259.987 | E11: =IF(SUMIFS('Standardized Data'!$G$2:$G$255,'Standardized Data'!$B$2:$B$255,$A11,'Standardized Data'!$A$2:$A$255,"Dec-2024")=0,"",SUMIFS('Standardized Data'!$G$2:$G$255,'Standardized Data'!$B$2:$B$255,$A11,'Standardized Data'!$A$2:$A$255,"Dec-2024")) -> 4347.4446 | F11: =IF(SUMIFS('Standardized Data'!$G$2:$G$255,'Standardized Data'!$B$2:$B$255,$A11,'Standardized Data'!$A$2:$A$255,"Jan-2025")=0,"",SUMIFS('Standardized Data'!$G$2:$G$255,'Standardized Data'!$B$2:$B$255,$A11,'Standardized Data'!$A$2:$A$255,"Jan-2025")) -> 5226.8706 | G11: =IF(SUMIFS('Standardized Data'!$G$2:$G$255,'Standardized Data'!$B$2:$B$255,$A11,'Standardized Data'!$A$2:$A$255,"Feb-2025")=0,"",SUMIFS('Standardized Data'!$G$2:$G$255,'Standardized Data'!$B$2:$B$255,$A11,'Standardized Data'!$A$2:$A$255,"Feb-2025")) -> 5284.3595 | H11: =IF(SUMIFS('Standardized Data'!$G$2:$G$255,'Standardized Data'!$B$2:$B$255,$A11,'Standardized Data'!$A$2:$A$255,"Mar-2025")=0,"",SUMIFS('Standardized Data'!$G$2:$G$255,'Standardized Data'!$B$2:$B$255,$A11,'Standardized Data'!$A$2:$A$255,"Mar-2025")) -> 5507.1099 | I11: =IF(SUMIFS('Standardized Data'!$G$2:$G$255,'Standardized Data'!$B$2:$B$255,$A11,'Standardized Data'!$A$2:$A$255,"Apr-2025")=0,"",SUMIFS('Standardized Data'!$G$2:$G$255,'Standardized Data'!$B$2:$B$255,$A11,'Standardized Data'!$A$2:$A$255,"Apr-2025")) -> 5572.4934 | J11: =IFERROR(AVERAGEIFS('Standardized Data'!$H$2:$H$255,'Standardized Data'!$B$2:$B$255,$A11),"") -> 5.2442352 | K11: =IFERROR(AVERAGEIFS('Standardized Data'!$I$2:$I$255,'Standardized Data'!$B$2:$B$255,$A11),"") -> 89.230786 | L11: =IF(I11<>"",I11,IF(H11<>"",H11,IF(G11<>"",G11,IF(F11<>"",F11,IF(E11<>"",E11,IF(D11<>"",D11,"")))))) -> 5572.4934
A12: Catfish :dried | B12: =IFERROR(INDEX('Standardized Data'!$D$2:$D$255,MATCH($A12,'Standardized Data'!$B$2:$B$255,0)),"") -> Discontinued | C12: =COUNTIF('Standardized Data'!$B$2:$B$255,$A12) -> 2 | D12: =IF(SUMIFS('Standardized Data'!$G$2:$G$255,'Standardized Data'!$B$2:$B$255,$A12,'Standardized Data'!$A$2:$A$255,"Nov-2024")=0,"",SUMIFS('Standardized Data'!$G$2:$G$255,'Standardized Data'!$B$2:$B$255,$A12,'Standardized Data'!$A$2:$A$255,"Nov-2024")) -> 5787.7445 | E12: =IF(SUMIFS('Standardized Data'!$G$2:$G$255,'Standardized Data'!$B$2:$B$255,$A12,'Standardized Data'!$A$2:$A$255,"Dec-2024")=0,"",SUMIFS('Standardized Data'!$G$2:$G$255,'Standardized Data'!$B$2:$B$255,$A12,'Standardized Data'!$A$2:$A$255,"Dec-2024")) -> 6044.0788 | F12: =IF(SUMIFS('Standardized Data'!$G$2:$G$255,'Standardized Data'!$B$2:$B$255,$A12,'Standardized Data'!$A$2:$A$255,"Jan-2025")=0,"",SUMIFS('Standardized Data'!$G$2:$G$255,'Standardized Data'!$B$2:$B$255,$A12,'Standardized Data'!$A$2:$A$255,"Jan-2025")) | G12: =IF(SUMIFS('Standardized Data'!$G$2:$G$255,'Standardized Data'!$B$2:$B$255,$A12,'Standardized Data'!$A$2:$A$255,"Feb-2025")=0,"",SUMIFS('Standardized Data'!$G$2:$G$255,'Standardized Data'!$B$2:$B$255,$A12,'Standardized Data'!$A$2:$A$255,"Feb-2025")) | H12: =IF(SUMIFS('Standardized Data'!$G$2:$G$255,'Standardized Data'!$B$2:$B$255,$A12,'Standardized Data'!$A$2:$A$255,"Mar-2025")=0,"",SUMIFS('Standardized Data'!$G$2:$G$255,'Standardized Data'!$B$2:$B$255,$A12,'Standardized Data'!$A$2:$A$255,"Mar-2025")) | I12: =IF(SUMIFS('Standardized Data'!$G$2:$G$255,'Standardized Data'!$B$2:$B$255,$A12,'Standardized Data'!$A$2:$A$255,"Apr-2025")=0,"",SUMIFS('Standardized Data'!$G$2:$G$255,'Standardized Data'!$B$2:$B$255,$A12,'Standardized Data'!$A$2:$A$255,"Apr-2025")) | J12: =IFERROR(AVERAGEIFS('Standardized Data'!$H$2:$H$255,'Standardized Data'!$B$2:$B$255,$A12),"") -> 4.1556295 | K12: =IFERROR(AVERAGEIFS('Standardized Data'!$I$2:$I$255,'Standardized Data'!$B$2:$B$255,$A12),"") -> 78.326962 | L12: =IF(I12<>"",I12,IF(H12<>"",H12,IF(G12<>"",G12,IF(F12<>"",F12,IF(E12<>"",E12,IF(D12<>"",D12,"")))))) -> 6044.0788
A13: Catfish Smoked | B13: =IFERROR(INDEX('Standardized Data'!$D$2:$D$255,MATCH($A13,'Standardized Data'!$B$2:$B$255,0)),"") -> Discontinued | C13: =COUNTIF('Standardized Data'!$B$2:$B$255,$A13) -> 2 | D13: =IF(SUMIFS('Standardized Data'!$G$2:$G$255,'Standardized Data'!$B$2:$B$255,$A13,'Standardized Data'!$A$2:$A$255,"Nov-2024")=0,"",SUMIFS('Standardized Data'!$G$2:$G$255,'Standardized Data'!$B$2:$B$255,$A13,'Standardized Data'!$A$2:$A$255,"Nov-2024")) -> 4352.7683 | E13: =IF(SUMIFS('Standardized Data'!$G$2:$G$255,'Standardized Data'!$B$2:$B$255,$A13,'Standardized Data'!$A$2:$A$255,"Dec-2024")=0,"",SUMIFS('Standardized Data'!$G$2:$G$255,'Standardized Data'!$B$2:$B$255,$A13,'Standardized Data'!$A$2:$A$255,"Dec-2024")) -> 4475.0964 | F13: =IF(SUMIFS('Standardized Data'!$G$2:$G$255,'Standardized Data'!$B$2:$B$255,$A13,'Standardized Data'!$A$2:$A$255,"Jan-2025")=0,"",SUMIFS('Standardized Data'!$G$2:$G$255,'Standardized Data'!$B$2:$B$255,$A13,'Standardized Data'!$A$2:$A$255,"Jan-2025")) | G13: =IF(SUMIFS('Standardized Data'!$G$2:$G$255,'Standardized Data'!$B$2:$B$255,$A13,'Standardized Data'!$A$2:$A$255,"Feb-2025")=0,"",SUMIFS('Standardized Data'!$G$2:$G$255,'Standardized Data'!$B$2:$B$255,$A13,'Standardized Data'!$A$2:$A$255,"Feb-2025")) | H13: =IF(SUMIFS('Standardized Data'!$G$2:$G$255,'Standardized Data'!$B$2:$B$255,$A13,'Standardized Data'!$A$2:$A$255,"Mar-2025")=0,"",SUMIFS('Standardized Data'!$G$2:$G$255,'Standardized Data'!$B$2:$B$255,$A13,'Standardized Data'!$A$2:$A$255,"Mar-2025")) | I13: =IF(SUMIFS('Standardized Data'!$G$2:$G$255,'Standardized Data'!$B$2:$B$255,$A13,'Standardized Data'!$A$2:$A$255,"Apr-2025")=0,"",SUMIFS('Standardized Data'!$G$2:$G$255,'Standardized Data'!$B$2:$B$255,$A13,'Standardized Data'!$A$2:$A$255,"Apr-2025")) | J13: =IFERROR(AVERAGEIFS('Standardized Data'!$H$2:$H$255,'Standardized Data'!$B$2:$B$255,$A13),"") -> 2.7351371 | K13: =IFERROR(AVERAGEIFS('Standardized Data'!$I$2:$I$255,'Standardized Data'!$B$2:$B$255,$A13),"") -> 55.252703 | L13: =IF(I13<>"",I13,IF(H13<>"",H13,IF(G13<>"",G13,IF(F13<>"",F13,IF(E13<>"",E13,IF(D13<>"",D13,"")))))) -> 4475.0964
... A53: Yam Tuber | B53: =IFERROR(INDEX('Standardized Data'!$D$2:$D$255,MATCH($A53,'Standardized Data'!$B$2:$B$255,0)),"") -> Confirmed | C53: =COUNTIF('Standardized Data'!$B$2:$B$255,$A53) -> 6 | D53: =IF(SUMIFS('Standardized Data'!$G$2:$G$255,'Standardized Data'!$B$2:$B$255,$A53,'Standardized Data'!$A$2:$A$255,"Nov-2024")=0,"",SUMIFS('Standardized Data'!$G$2:$G$255,'Standardized Data'!$B$2:$B$255,$A53,'Standardized Data'!$A$2:$A$255,"Nov-2024")) -> 1836.0085 | E53: =IF(SUMIFS('Standardized Data'!$G$2:$G$255,'Standardized Data'!$B$2:$B$255,$A53,'Standardized Data'!$A$2:$A$255,"Dec-2024")=0,"",SUMIFS('Standardized Data'!$G$2:$G$255,'Standardized Data'!$B$2:$B$255,$A53,'Standardized Data'!$A$2:$A$255,"Dec-2024")) -> 1905.901 | F53: =IF(SUMIFS('Standardized Data'!$G$2:$G$255,'Standardized Data'!$B$2:$B$255,$A53,'Standardized Data'!$A$2:$A$255,"Jan-2025")=0,"",SUMIFS('Standardized Data'!$G$2:$G$255,'Standardized Data'!$B$2:$B$255,$A53,'Standardized Data'!$A$2:$A$255,"Jan-2025")) -> 1991.3299 | G53: =IF(SUMIFS('Standardized Data'!$G$2:$G$255,'Standardized Data'!$B$2:$B$255,$A53,'Standardized Data'!$A$2:$A$255,"Feb-2025")=0,"",SUMIFS('Standardized Data'!$G$2:$G$255,'Standardized Data'!$B$2:$B$255,$A53,'Standardized Data'!$A$2:$A$255,"Feb-2025")) -> 2022.0329 | H53: =IF(SUMIFS('Standardized Data'!$G$2:$G$255,'Standardized Data'!$B$2:$B$255,$A53,'Standardized Data'!$A$2:$A$255,"Mar-2025")=0,"",SUMIFS('Standardized Data'!$G$2:$G$255,'Standardized Data'!$B$2:$B$255,$A53,'Standardized Data'!$A$2:$A$255,"Mar-2025")) -> 2141.13 | I53: =IF(SUMIFS('Standardized Data'!$G$2:$G$255,'Standardized Data'!$B$2:$B$255,$A53,'Standardized Data'!$A$2:$A$255,"Apr-2025")=0,"",SUMIFS('Standardized Data'!$G$2:$G$255,'Standardized Data'!$B$2:$B$255,$A53,'Standardized Data'!$A$2:$A$255,"Apr-2025")) -> 2240.0838 | J53: =IFERROR(AVERAGEIFS('Standardized Data'!$H$2:$H$255,'Standardized Data'!$B$2:$B$255,$A53),"") -> 4.6649022 | K53: =IFERROR(AVERAGEIFS('Standardized Data'!$I$2:$I$255,'Standardized Data'!$B$2:$B$255,$A53),"") -> 114.98585 | L53: =IF(I53<>"",I53,IF(H53<>"",H53,IF(G53<>"",G53,IF(F53<>"",F53,IF(E53<>"",E53,IF(D53<>"",D53,"")))))) -> 2240.0838

Sheet State Summary
A1: State | B1: Times Highest | C1: Times Lowest | D1: Avg Price When Highest | E1: Avg Price When Lowest
A2: Abia | B2: =COUNTIF('Standardized Data'!$K$2:$K$255,$A2) -> 9 | C2: =COUNTIF('Standardized Data'!$N$2:$N$255,$A2) -> 2 | D2: =IFERROR(AVERAGEIF('Standardized Data'!$K$2:$K$255,$A2,'Standardized Data'!$L$2:$L$255),"") -> 5523.34 | E2: =IFERROR(AVERAGEIF('Standardized Data'!$N$2:$N$255,$A2,'Standardized Data'!$O$2:$O$255),"") -> 3063.96
A3: Abuja | B3: =COUNTIF('Standardized Data'!$K$2:$K$255,$A3) -> 7 | C3: =COUNTIF('Standardized Data'!$N$2:$N$255,$A3) -> 10 | D3: =IFERROR(AVERAGEIF('Standardized Data'!$K$2:$K$255,$A3,'Standardized Data'!$L$2:$L$255),"") -> 3234.5814 | E3: =IFERROR(AVERAGEIF('Standardized Data'!$N$2:$N$255,$A3,'Standardized Data'!$O$2:$O$255),"") -> 1714.899
A4: Adamawa | B4: =COUNTIF('Standardized Data'!$K$2:$K$255,$A4) -> 3 | C4: =COUNTIF('Standardized Data'!$N$2:$N$255,$A4) -> 21 | D4: =IFERROR(AVERAGEIF('Standardized Data'!$K$2:$K$255,$A4,'Standardized Data'!$L$2:$L$255),"") -> 2679 | E4: =IFERROR(AVERAGEIF('Standardized Data'!$N$2:$N$255,$A4,'Standardized Data'!$O$2:$O$255),"") -> 1744.0476
A5: Akwa Ibom | B5: =COUNTIF('Standardized Data'!$K$2:$K$255,$A5) -> 11 | C5: =COUNTIF('Standardized Data'!$N$2:$N$255,$A5) -> 1 | D5: =IFERROR(AVERAGEIF('Standardized Data'!$K$2:$K$255,$A5,'Standardized Data'!$L$2:$L$255),"") -> 4831.7627 | E5: =IFERROR(AVERAGEIF('Standardized Data'!$N$2:$N$255,$A5,'Standardized Data'!$O$2:$O$255),"") -> 4576.03
A6: Anambra | B6: =COUNTIF('Standardized Data'!$K$2:$K$255,$A6) -> 6 | C6: =COUNTIF('Standardized Data'!$N$2:$N$255,$A6) -> 1 | D6: =IFERROR(AVERAGEIF('Standardized Data'!$K$2:$K$255,$A6,'Standardized Data'!$L$2:$L$255),"") -> 2959.575 | E6: =IFERROR(AVERAGEIF('Standardized Data'!$N$2:$N$255,$A6,'Standardized Data'!$O$2:$O$255),"") -> 3650.97
A7: Bauchi | B7: =COUNTIF('Standardized Data'!$K$2:$K$255,$A7) -> 3 | C7: =COUNTIF('Standardized Data'!$N$2:$N$255,$A7) -> 5 | D7: =IFERROR(AVERAGEIF('Standardized Data'!$K$2:$K$255,$A7,'Standardized Data'!$L$2:$L$255),"") -> 2492.0167 | E7: =IFERROR(AVERAGEIF('Standardized Data'!$N$2:$N$255,$A7,'Standardized Data'!$O$2:$O$255),"") -> 2340.084
A8: Bayelsa | B8: =COUNTIF('Standardized Data'!$K$2:$K$255,$A8) -> 8 | C8: =COUNTIF('Standardized Data'!$N$2:$N$255,$A8) -> 6 | D8: =IFERROR(AVERAGEIF('Standardized Data'!$K$2:$K$255,$A8,'Standardized Data'!$L$2:$L$255),"") -> 3253.4825 | E8: =IFERROR(AVERAGEIF('Standardized Data'!$N$2:$N$255,$A8,'Standardized Data'!$O$2:$O$255),"") -> 3084.9867
A9: Benue | B9: =COUNTIF('Standardized Data'!$K$2:$K$255,$A9) -> 4 | C9: =COUNTIF('Standardized Data'!$N$2:$N$255,$A9) -> 16 | D9: =IFERROR(AVERAGEIF('Standardized Data'!$K$2:$K$255,$A9,'Standardized Data'!$L$2:$L$255),"") -> 8281.5175 | E9: =IFERROR(AVERAGEIF('Standardized Data'!$N$2:$N$255,$A9,'Standardized Data'!$O$2:$O$255),"") -> 1839.5137
A10: Borno | B10: =COUNTIF('Standardized Data'!$K$2:$K$255,$A10) -> 2 | C10: =COUNTIF('Standardized Data'!$N$2:$N$255,$A10) -> 15 | D10: =IFERROR(AVERAGEIF('Standardized Data'!$K$2:$K$255,$A10,'Standardized Data'!$L$2:$L$255),"") -> 3342.125 | E10: =IFERROR(AVERAGEIF('Standardized Data'!$N$2:$N$255,$A10,'Standardized Data'!$O$2:$O$255),"") -> 1396.33
A11: Cross River | B11: =COUNTIF('Standardized Data'!$K$2:$K$255,$A11) -> 5 | C11: =COUNTIF('Standardized Data'!$N$2:$N$255,$A11) -> 0 | D11: =IFERROR(AVERAGEIF('Standardized Data'!$K$2:$K$255,$A11,'Standardized Data'!$L$2:$L$255),"") -> 2428.304 | E11: =IFERROR(AVERAGEIF('Standardized Data'!$N$2:$N$255,$A11,'Standardized Data'!$O$2:$O$255),"")
A12: Delta | B12: =COUNTIF('Standardized Data'!$K$2:$K$255,$A12) -> 4 | C12: =COUNTIF('Standardized Data'!$N$2:$N$255,$A12) -> 0 | D12: =IFERROR(AVERAGEIF('Standardized Data'!$K$2:$K$255,$A12,'Standardized Data'!$L$2:$L$255),"") -> 1572.7125 | E12: =IFERROR(AVERAGEIF('Standardized Data'!$N$2:$N$255,$A12,'Standardized Data'!$O$2:$O$255),"")
A13: Ebonyi | B13: =COUNTIF('Standardized Data'!$K$2:$K$255,$A13) -> 19 | C13: =COUNTIF('Standardized Data'!$N$2:$N$255,$A13) -> 1 | D13: =IFERROR(AVERAGEIF('Standardized Data'!$K$2:$K$255,$A13,'Standardized Data'!$L$2:$L$255),"") -> 4685.0547 | E13: =IFERROR(AVERAGEIF('Standardized Data'!$N$2:$N$255,$A13,'Standardized Data'!$O$2:$O$255),"") -> 2394.41
... A38: Zamfara | B38: =COUNTIF('Standardized Data'!$K$2:$K$255,$A38) -> 1 | C38: =COUNTIF('Standardized Data'!$N$2:$N$255,$A38) -> 9 | D38: =IFERROR(AVERAGEIF('Standardized Data'!$K$2:$K$255,$A38,'Standardized Data'!$L$2:$L$255),"") -> 3235.2 | E38: =IFERROR(AVERAGEIF('Standardized Data'!$N$2:$N$255,$A38,'Standardized Data'!$O$2:$O$255),"") -> 2252.9878

Sheet Top Movers
A1: Top 10 Items by Average YoY Inflation (Nov'24–Apr'25) | D1: Top 10 Items by Average MoM Increase | G1: Top 10 States — Most Often the Highest-Price State | J1: Top 10 States — Most Often the Lowest-Price State
A2: Item | B2: Avg YoY % | D2: Item | E2: Avg MoM % | G2: State | H2: Times Highest | J2: State | K2: Times Lowest
A3: Local Rice (Broken) | B3: =IFERROR(INDEX('Item Summary'!$K$2:$K$53,MATCH($A3,'Item Summary'!$A$2:$A$53,0)),"") -> 157.51878 | D3: Plantain (unripe) | E3: =IFERROR(INDEX('Item Summary'!$J$2:$J$53,MATCH($D3,'Item Summary'!$A$2:$A$53,0)),"") -> 7.1114422 | G3: Enugu | H3: =IFERROR(INDEX('State Summary'!$B$2:$B$38,MATCH($G3,'State Summary'!$A$2:$A$38,0)),"") -> 25 | J3: Yobe | K3: =IFERROR(INDEX('State Summary'!$C$2:$C$38,MATCH($J3,'State Summary'!$A$2:$A$38,0)),"") -> 29
A4: Beans Brown | B4: =IFERROR(INDEX('Item Summary'!$K$2:$K$53,MATCH($A4,'Item Summary'!$A$2:$A$53,0)),"") -> 143.28973 | D4: Onions, fresh | E4: =IFERROR(INDEX('Item Summary'!$J$2:$J$53,MATCH($D4,'Item Summary'!$A$2:$A$53,0)),"") -> 5.963605 | G4: Imo | H4: =IFERROR(INDEX('State Summary'!$B$2:$B$38,MATCH($G4,'State Summary'!$A$2:$A$38,0)),"") -> 22 | J4: Adamawa | K4: =IFERROR(INDEX('State Summary'!$C$2:$C$38,MATCH($J4,'State Summary'!$A$2:$A$38,0)),"") -> 21
A5: Plantain (unripe) | B5: =IFERROR(INDEX('Item Summary'!$K$2:$K$53,MATCH($A5,'Item Summary'!$A$2:$A$53,0)),"") -> 133.72148 | D5: Tilapia fresh fish (Epiya) | E5: =IFERROR(INDEX('Item Summary'!$J$2:$J$53,MATCH($D5,'Item Summary'!$A$2:$A$53,0)),"") -> 5.9485833 | G5: Ebonyi | H5: =IFERROR(INDEX('State Summary'!$B$2:$B$38,MATCH($G5,'State Summary'!$A$2:$A$38,0)),"") -> 19 | J5: Oyo | K5: =IFERROR(INDEX('State Summary'!$C$2:$C$38,MATCH($J5,'State Summary'!$A$2:$A$38,0)),"") -> 18
A6: Agric hen eggs, (a Crate of 30 pieces) | B6: =IFERROR(INDEX('Item Summary'!$K$2:$K$53,MATCH($A6,'Item Summary'!$A$2:$A$53,0)),"") -> 132.09737 | D6: Ginger, fresh | E6: =IFERROR(INDEX('Item Summary'!$J$2:$J$53,MATCH($D6,'Item Summary'!$A$2:$A$53,0)),"") -> 5.7332267 | G6: Plateau | H6: =IFERROR(INDEX('State Summary'!$B$2:$B$38,MATCH($G6,'State Summary'!$A$2:$A$38,0)),"") -> 19 | J6: Taraba | K6: =IFERROR(INDEX('State Summary'!$C$2:$C$38,MATCH($J6,'State Summary'!$A$2:$A$38,0)),"") -> 17
A7: Beans white | B7: =IFERROR(INDEX('Item Summary'!$K$2:$K$53,MATCH($A7,'Item Summary'!$A$2:$A$53,0)),"") -> 126.05759 | D7: Plantain (ripe) | E7: =IFERROR(INDEX('Item Summary'!$J$2:$J$53,MATCH($D7,'Item Summary'!$A$2:$A$53,0)),"") -> 5.5793612 | G7: Gombe | H7: =IFERROR(INDEX('State Summary'!$B$2:$B$38,MATCH($G7,'State Summary'!$A$2:$A$38,0)),"") -> 15 | J7: Benue | K7: =IFERROR(INDEX('State Summary'!$C$2:$C$38,MATCH($J7,'State Summary'!$A$2:$A$38,0)),"") -> 16
A8: Rice Medium Grained | B8: =IFERROR(INDEX('Item Summary'!$K$2:$K$53,MATCH($A8,'Item Summary'!$A$2:$A$53,0)),"") -> 117.94772 | D8: Cat fresh fish | E8: =IFERROR(INDEX('Item Summary'!$J$2:$J$53,MATCH($D8,'Item Summary'!$A$2:$A$53,0)),"") -> 5.2442352 | G8: Ogun | H8: =IFERROR(INDEX('State Summary'!$B$2:$B$38,MATCH($G8,'State Summary'!$A$2:$A$38,0)),"") -> 14 | J8: Borno | K8: =IFERROR(INDEX('State Summary'!$C$2:$C$38,MATCH($J8,'State Summary'!$A$2:$A$38,0)),"") -> 15
A9: Plantain (ripe) | B9: =IFERROR(INDEX('Item Summary'!$K$2:$K$53,MATCH($A9,'Item Summary'!$A$2:$A$53,0)),"") -> 116.2034 | D9: Titus, frozen | E9: =IFERROR(INDEX('Item Summary'!$J$2:$J$53,MATCH($D9,'Item Summary'!$A$2:$A$53,0)),"") -> 4.8128487 | G9: Akwa Ibom | H9: =IFERROR(INDEX('State Summary'!$B$2:$B$38,MATCH($G9,'State Summary'!$A$2:$A$38,0)),"") -> 11 | J9: Niger | K9: =IFERROR(INDEX('State Summary'!$C$2:$C$38,MATCH($J9,'State Summary'!$A$2:$A$38,0)),"") -> 13
A10: Rice agric sold loose | B10: =IFERROR(INDEX('Item Summary'!$K$2:$K$53,MATCH($A10,'Item Summary'!$A$2:$A$53,0)),"") -> 116.1475 | D10: Mackerel, Frozen | E10: =IFERROR(INDEX('Item Summary'!$J$2:$J$53,MATCH($D10,'Item Summary'!$A$2:$A$53,0)),"") -> 4.8038654 | G10: Kwara | H10: =IFERROR(INDEX('State Summary'!$B$2:$B$38,MATCH($G10,'State Summary'!$A$2:$A$38,0)),"") -> 11 | J10: Kogi | K10: =IFERROR(INDEX('State Summary'!$C$2:$C$38,MATCH($J10,'State Summary'!$A$2:$A$38,0)),"") -> 13
A11: Yam Tuber | B11: =IFERROR(INDEX('Item Summary'!$K$2:$K$53,MATCH($A11,'Item Summary'!$A$2:$A$53,0)),"") -> 114.98585 | D11: Groundnut oil, 75cl | E11: =IFERROR(INDEX('Item Summary'!$J$2:$J$53,MATCH($D11,'Item Summary'!$A$2:$A$53,0)),"") -> 4.6975734 | G11: Kogi | H11: =IFERROR(INDEX('State Summary'!$B$2:$B$38,MATCH($G11,'State Summary'!$A$2:$A$38,0)),"") -> 10 | J11: Kebbi | K11: =IFERROR(INDEX('State Summary'!$C$2:$C$38,MATCH($J11,'State Summary'!$A$2:$A$38,0)),"") -> 11
A12: Tilapia fresh fish (Epiya) | B12: =IFERROR(INDEX('Item Summary'!$K$2:$K$53,MATCH($A12,'Item Summary'!$A$2:$A$53,0)),"") -> 105.83782 | D12: Mudfish : dried | E12: =IFERROR(INDEX('Item Summary'!$J$2:$J$53,MATCH($D12,'Item Summary'!$A$2:$A$53,0)),"") -> 4.682831 | G12: Ekiti | H12: =IFERROR(INDEX('State Summary'!$B$2:$B$38,MATCH($G12,'State Summary'!$A$2:$A$38,0)),"") -> 10 | J12: Abuja | K12: =IFERROR(INDEX('State Summary'!$C$2:$C$38,MATCH($J12,'State Summary'!$A$2:$A$38,0)),"") -> 10

Sheet Mapping Notes
A1: Standardized Item | B1: Original Label(s) Seen In Raw Data | C1: Match Confidence | D1: Note | E1: Months Covered
A2: Agric hen eggs | B2: Agric eggs(medium size price of one) | Agric hen eggs | Agric hen eggs, | C2: Confirmed | D2: Linked via matching Avg(Previous Month) value in Jan-2025 data | E2: Nov-2024, Dec-2024, Jan-2025, Feb-2025, Mar-2025, Apr-2025
A3: Beans Brown | B3: Beans Brown | Beans brown,sold loose | C3: Confirmed | D3: Linked via matching Avg(Previous Month) value in Jan-2025 data | E3: Nov-2024, Dec-2024, Jan-2025, Feb-2025, Mar-2025, Apr-2025
A4: Beans white | B4: Beans white | Beans:white black eye. sold loose | C4: Confirmed | D4: Linked via matching Avg(Previous Month) value in Jan-2025 data | E4: Nov-2024, Dec-2024, Jan-2025, Feb-2025, Mar-2025, Apr-2025
A5: Beef Boneless | B5: Beef Boneless | Beef,boneless | C5: Confirmed | D5: Linked via matching Avg(Previous Month) value in Jan-2025 data | E5: Nov-2024, Dec-2024, Jan-2025, Feb-2025, Mar-2025, Apr-2025
A6: Cat fresh fish | B6: Cat fresh fish | Catfish (obokun) fresh | C6: Confirmed | D6: Linked via matching Avg(Previous Month) value in Jan-2025 data | E6: Nov-2024, Dec-2024, Jan-2025, Feb-2025, Mar-2025, Apr-2025
A7: Chicken Wings | B7: Chicken Wings | C7: Confirmed | D7: Linked via matching Avg(Previous Month) value in Jan-2025 data | E7: Nov-2024, Dec-2024, Jan-2025, Feb-2025, Mar-2025, Apr-2025
A8: Chicken feet | B8: Chicken Feet | Chicken feet | C8: Confirmed | D8: Linked via matching Avg(Previous Month) value in Jan-2025 data | E8: Nov-2024, Dec-2024, Jan-2025, Feb-2025, Mar-2025, Apr-2025
A9: Chicken meat (Frozen) | B9: Chicken meat (Frozen) | Frozen chicken | C9: Confirmed | D9: Linked via matching Avg(Previous Month) value in Jan-2025 data | E9: Nov-2024, Dec-2024, Jan-2025, Feb-2025, Mar-2025, Apr-2025
A10: Garri Yellow | B10: Gari yellow,sold loose | Garri Yellow | C10: Confirmed | D10: Linked via matching Avg(Previous Month) value in Jan-2025 data | E10: Nov-2024, Dec-2024, Jan-2025, Feb-2025, Mar-2025, Apr-2025
A11: Garri white | B11: Gari white,sold loose | Garri white | C11: Confirmed | D11: Linked via matching Avg(Previous Month) value in Jan-2025 data | E11: Nov-2024, Dec-2024, Jan-2025, Feb-2025, Mar-2025, Apr-2025
A12: Irish Potatoe | B12: Irish Potatoe | Irish potato | C12: Confirmed | D12: Linked via matching Avg(Previous Month) value in Jan-2025 data | E12: Nov-2024, Dec-2024, Jan-2025, Feb-2025, Mar-2025, Apr-2025
... A53: Watermelon whole, medium size fresh | B53: Watermelon whole, medium size fresh | C53: New (2025) | D53: Introduced starting Jan-2025; no predecessor in Nov-Dec 2024 list | E53: Jan-2025, Feb-2025, Mar-2025, Apr-2025

Sheet Raw Data (Original)
A1: Month | B1: Source File | C1: Item Label | D1: Avg (Same Month Last Year) | E1: Avg (Previous Month) | F1: Avg (Current Month) | G1: MoM | H1: YoY | I1: Highest | J1: Lowest
A2: Nov-2024 | B2: selected_food_Nov_2024.xlsx | C2: Agric eggs medium size | D2: 1202.1768 | E2: 2671.6021 | F2: 2833.973 | G2: 6.0776605 | H2: 135.7368 | I2: Gombe (3600) | J2: Borno (2381.15)
A3: Nov-2024 | B3: selected_food_Nov_2024.xlsx | C3: Agric eggs(medium size price of one) | D3: 110.09887 | E3: 235.6735 | F3: 247.2591 | G3: 4.9159544 | H3: 124.57914 | I3: Gombe (300) | J3: Borno (199.73)
A4: Nov-2024 | B4: selected_food_Nov_2024.xlsx | C4: Beans brown,sold loose | D4: 838.84915 | E4: 2798.4962 | F4: 2720.9608 | G4: -2.7706082 | H4: 224.36831 | I4: Bauchi (3675) | J4: Adamawa (1925)
A5: Nov-2024 | B5: selected_food_Nov_2024.xlsx | C5: Beans:white black eye. sold loose | D5: 800.48677 | E5: 2603.318 | F5: 2546.7025 | G5: -2.1747433 | H5: 218.14424 | I5: Ebonyi (3157.2) | J5: Adamawa (1750)
A6: Nov-2024 | B6: selected_food_Nov_2024.xlsx | C6: Beef Bone in | D6: 2630.0152 | E6: 4914.6219 | F6: 5073.7358 | G6: 3.237562 | H6: 92.916594 | I6: Niger (6244.03) | J6: Anambra (3650.97)
A7: Nov-2024 | B7: selected_food_Nov_2024.xlsx | C7: Beef,boneless | D7: 3029.501 | E7: 5858.5767 | F7: 6001.3163 | G7: 2.4364204 | H7: 98.09587 | I7: Enugu (7020.85) | J7: Yobe (4800)
A8: Nov-2024 | B8: selected_food_Nov_2024.xlsx | C8: Bread sliced 500g | D8: 814.53125 | E8: 1550.2427 | F8: 1588.0267 | G8: 2.4372917 | H8: 94.962032 | I8: Rivers (1881.67) | J8: Yobe (1120.4)
A9: Nov-2024 | B9: selected_food_Nov_2024.xlsx | C9: Bread unsliced 500g | D9: 795.82989 | E9: 1454.4362 | F9: 1486.2466 | G9: 2.1871298 | H9: 86.754307 | I9: Delta (1805.42) | J9: Borno (1053.56)
A10: Nov-2024 | B10: selected_food_Nov_2024.xlsx | C10: Broken Rice (Ofada) | D10: 940.15974 | E10: 2428.6473 | F10: 2485.1389 | G10: 2.3260488 | H10: 164.33156 | I10: Osun (3400) | J10: Adamawa (1500)
A11: Nov-2024 | B11: selected_food_Nov_2024.xlsx | C11: Catfish (obokun) fresh | D11: 2231.2344 | E11: 4148.7414 | F11: 4259.987 | G11: 2.6814298 | H11: 90.925119 | I11: Bayelsa (5885.71) | J11: Adamawa (3000)
A12: Nov-2024 | B12: selected_food_Nov_2024.xlsx | C12: Catfish :dried | D12: 3276.6289 | E12: 5571.442 | F12: 5787.7445 | G12: 3.8823436 | H12: 76.63717 | I12: Imo (12181.27) | J12: Kano (3950.44)
A13: Nov-2024 | B13: selected_food_Nov_2024.xlsx | C13: Catfish Smoked | D13: 2816.4811 | E13: 4239.9879 | F13: 4352.7683 | G13: 2.6599243 | H13: 54.546335 | I13: Yobe (6255.22) | J13: Kebbi (3391.67)
... A88: Jan-2025 | B88: Selected_food_table_Jan25.xlsx | C88: Agric hen eggs | D88: 116.41 | E88: 252.1655 | F88: 248.04139 | G88: -1.6354765 | H88: 113.07567 | I88: Enugu (325) | J88: Adamawa (200)
A89: Jan-2025 | B89: Selected_food_table_Jan25.xlsx | C89: Agric hen eggs, (a Crate of 30 pieces) | F89: 5878.1406 | I89: Enugu (7000) | J89: Niger (4613.06)
A90: Jan-2025 | B90: Selected_food_table_Jan25.xlsx | C90: Beans Brown | D90: 976.58407 | E90: 2501.3235 | F90: 2458.5333 | G90: -1.7107038 | H90: 151.74825 | I90: Abia (3230.87) | J90: Sokoto (1575.36)
A91: Jan-2025 | B91: Selected_food_table_Jan25.xlsx | C91: Beans white | D91: 921.37822 | E91: 2319.0422 | F91: 2123.853 | G91: -8.4168028 | H91: 130.50827 | I91: Enugu (2722.76) | J91: Sokoto (1370.59)
A92: Jan-2025 | B92: Selected_food_table_Jan25.xlsx | C92: Beef Boneless | D92: 3315.7811 | E92: 6150.1829 | F92: 6122.5683 | G92: -0.44900434 | H92: 84.649351 | I92: Imo (8239.82) | J92: Benue (4200)
A93: Jan-2025 | B93: Selected_food_table_Jan25.xlsx | C93: Bread (sliced), 450g | F93: 1604.7842 | I93: Ogun (1950) | J93: Osun (1300)
A94: Jan-2025 | B94: Selected_food_table_Jan25.xlsx | C94: Bread (unsliced), 450g | F94: 1452.983 | I94: Akwa Ibom (1800) | J94: Yobe (900)
A95: Jan-2025 | B95: Selected_food_table_Jan25.xlsx | C95: Carrots, fresh | F95: 1787.1615 | I95: Bayelsa (2572.73) | J95: Benue (1400)
A96: Jan-2025 | B96: Selected_food_table_Jan25.xlsx | C96: Cat fresh fish | D96: 2497.3741 | E96: 4347.4446 | F96: 5226.8706 | G96: 20.228574 | H96: 109.29466 | I96: Plateau (7608.1) | J96: Kaduna (3442.5)
A97: Jan-2025 | B97: Selected_food_table_Jan25.xlsx | C97: Chicken feet | D97: 2052.1003 | E97: 3397.8334 | F97: 3293.6296 | G97: -3.0667712 | H97: 60.500418 | I97: Ondo (4750) | J97: Taraba (2000)
A98: Jan-2025 | B98: Selected_food_table_Jan25.xlsx | C98: Chicken meat (Frozen) | D98: 4007.5773 | E98: 6473.8064 | F98: 5497.0311 | G98: -15.088114 | H98: 37.165941 | I98: Ebonyi (7800) | J98: Sokoto (4000)
A99: Jan-2025 | B99: Selected_food_table_Jan25.xlsx | C99: Chicken Wings | D99: 2506.8092 | E99: 4422.8022 | F99: 4340.1078 | G99: -1.8697281 | H99: 73.132752 | I99: Niger (5703.26) | J99: Yobe (2709.25)
A100: Jan-2025 | B100: Selected_food_table_Jan25.xlsx | C100: Cray fish small white | F100: 6227.0407 | I100: Abuja (7800) | J100: Bayelsa (4000)
A101: Jan-2025 | B101: Selected_food_table_Jan25.xlsx | C101: Dried fish, Bonga | F101: 6131.9801 | I101: Enugu (8900) | J101: Bayelsa (4202.78)
A102: Jan-2025 | B102: Selected_food_table_Jan25.xlsx | C102: Garri white | D102: 600.6872 | E102: 1184.7662 | F102: 1267.6349 | G102: 6.9945192 | H102: 111.03078 | I102: Abuja (1662.11) | J102: Oyo (909.09)
A103: Jan-2025 | B103: Selected_food_table_Jan25.xlsx | C103: Garri Yellow | D103: 624.21266 | E103: 1296.9267 | F103: 1358.9584 | G103: 4.7829754 | H103: 117.7076 | I103: Gombe (1692.31) | J103: Benue (980.24)
A104: Jan-2025 | B104: Selected_food_table_Jan25.xlsx | C104: Ginger, fresh | F104: 4206.7995 | I104: Oyo (5000) | J104: Katsina (2550)
A105: Jan-2025 | B105: Selected_food_table_Jan25.xlsx | C105: Goat Meat Bone in | F105: 6202.3575 | I105: Akwa Ibom (8687.5) | J105: Kogi (3925)
A106: Jan-2025 | B106: Selected_food_table_Jan25.xlsx | C106: Groundnut oil, 75cl | F106: 2939.7346 | I106: Ogun (3900) | J106: Adamawa (2000)
A107: Jan-2025 | B107: Selected_food_table_Jan25.xlsx | C107: Groundnuts, roasted,75cl bottle | F107: 2387.7568 | I107: Bayelsa (3125) | J107: Kano (1806.47)
A108: Jan-2025 | B108: Selected_food_table_Jan25.xlsx | C108: Irish Potatoe | D108: 1051.7684 | E108: 1818.2876 | F108: 1790.9109 | G108: -1.505634 | H108: 70.276157 | I108: Oyo (2687.5) | J108: Abuja (972.45)
A109: Jan-2025 | B109: Selected_food_table_Jan25.xlsx | C109: Local Rice (Broken) | F109: 2508.155 | I109: Ogun (4500) | J109: Yobe (1416.67)
A110: Jan-2025 | B110: Selected_food_table_Jan25.xlsx | C110: Mackerel, Frozen | D110: 2457.9635 | E110: 4287.654 | F110: 5117.8059 | G110: 19.361448 | H110: 108.21326 | I110: Plateau (8696.05) | J110: Zamfara (3196.67)
A111: Jan-2025 | B111: Selected_food_table_Jan25.xlsx | C111: Maize (Corn) Grains (White) sold loose | D111: 633.91205 | E111: 1151.1347 | F111: 1168.338 | G111: 1.494461 | H111: 84.306004 | I111: Imo (1762.5) | J111: Kebbi (692.27)
A112: Jan-2025 | B112: Selected_food_table_Jan25.xlsx | C112: Onions, fresh | D112: 881.19765 | E112: 2057.8109 | F112: 1367.6216 | G112: -33.539978 | H112: 55.200318 | I112: Cross River (2500) | J112: Taraba (520)
A113: Jan-2025 | B113: Selected_food_table_Jan25.xlsx | C113: Palm oil, 75cl | D113: 1456.7228 | E113: 2582.348 | F113: 2329.5428 | G113: -9.7897415 | H113: 59.91669 | I113: Ogun (3000) | J113: Taraba (1363.33)
A114: Jan-2025 | B114: Selected_food_table_Jan25.xlsx | C114: Plantain (ripe) | D114: 810.66698 | E114: 1533.681 | F114: 1876.0259 | G114: 22.32178 | H114: 131.41758 | I114: Akwa Ibom (2202.78) | J114: Lagos (1584.06)
A115: Jan-2025 | B115: Selected_food_table_Jan25.xlsx | C115: Plantain (unripe) | D115: 811.94517 | E115: 1550.1514 | F115: 2119.0689 | G115: 36.700773 | H115: 160.9867 | I115: Plateau (2821.97) | J115: Oyo (1564.71)
A116: Jan-2025 | B116: Selected_food_table_Jan25.xlsx | C116: Rice Local, short-Grained | D116: 1021.7857 | E116: 1944.4039 | F116: 2067.9978 | G116: 6.3563915 | H116: 102.39056 | I116: Plateau (2559.74) | J116: Oyo (1578.69)
A117: Jan-2025 | B117: Selected_food_table_Jan25.xlsx | C117: Rice Long-Grained (Imported) | D117: 1322.0056 | E117: 2520.7757 | F117: 2505.4794 | G117: -0.60681026 | H117: 89.521087 | I117: Plateau (3181.82) | J117: Oyo (1935.48)
A118: Jan-2025 | B118: Selected_food_table_Jan25.xlsx | C118: Semovita, Prepacked (1kg) | F118: 2072.0012 | I118: Rivers (2550) | J118: Oyo (1700)
A119: Jan-2025 | B119: Selected_food_table_Jan25.xlsx | C119: Smoked fish (Mackerel) | F119: 5407.6327 | I119: Kwara (8000) | J119: Kebbi (3360.04)
A120: Jan-2025 | B120: Selected_food_table_Jan25.xlsx | C120: Sweet potatoes | D120: 615.47258 | E120: 930.78901 | F120: 852.51531 | G120: -8.409392 | H120: 38.513938 | I120: Taraba (1700) | J120: Nasarawa (500)
A121: Jan-2025 | B121: Selected_food_table_Jan25.xlsx | C121: Tilapia fresh fish (Epiya) | D121: 2214.4284 | E121: 4106.7162 | F121: 5065.3632 | G121: 23.343395 | H121: 128.7436 | I121: Benue (8239.29) | J121: Kebbi (3692.11)
A122: Jan-2025 | B122: Selected_food_table_Jan25.xlsx | C122: Tin Milk-Evaporated, Peak Milk, 150g | D122: 575.78306 | E122: 1014.7415 | F122: 928.00163 | G122: -8.547974 | H122: 61.172096 | I122: Rivers (1150) | J122: Bayelsa (725)
A123: Jan-2025 | B123: Selected_food_table_Jan25.xlsx | C123: Tin Milk-Evaporated, Three Crown Milk, 160g | F123: 837.23255 | I123: Bayelsa (1200) | J123: Benue (675)
A124: Jan-2025 | B124: Selected_food_table_Jan25.xlsx | C124: Titus, frozen | D124: 2628.508 | E124: 4725.1654 | F124: 5467.2313 | G124: 15.704549 | H124: 107.99752 | I124: Kwara (8343.26) | J124: Taraba (4000)
A125: Jan-2025 | B125: Selected_food_table_Jan25.xlsx | C125: Tomatoes, fresh | D125: 845.25824 | E125: 1453.4957 | F125: 1081.4391 | G125: -25.597361 | H125: 27.941863 | I125: Ebonyi (1778.11) | J125: Kebbi (512.96)
A126: Jan-2025 | B126: Selected_food_table_Jan25.xlsx | C126: Vegetable Oil, 75cl | D126: 1782.7715 | E126: 3362.8341 | F126: 2975.9619 | G126: -11.504348 | H126: 66.928959 | I126: Ekiti (4616.67) | J126: Adamawa (1800)
A127: Jan-2025 | B127: Selected_food_table_Jan25.xlsx | C127: Watermelon whole, medium size fresh | F127: 1850.8433 | I127: Akwa Ibom (2500) | J127: Zamfara (1200)
A128: Jan-2025 | B128: Selected_food_table_Jan25.xlsx | C128: Wheat Flour, Prepacked (2kg) | D128: 2042.984 | E128: 3871.4754 | F128: 3847.3657 | G128: -0.62275338 | H128: 88.320896 | I128: Borno (5500) | J128: Bauchi (2700)
A129: Jan-2025 | B129: Selected_food_table_Jan25.xlsx | C129: Yam Tuber | D129: 901.94205 | E129: 1905.901 | F129: 1991.3299 | G129: 4.4823399 | H129: 120.78247 | I129: Ogun (2566.67) | J129: Ondo (1450)
A130: Feb-2025 | B130: selected_food_table_Feb_25.xlsx | C130: Agric hen eggs, | D130: 139.28021 | E130: 248.04139 | F130: 251.94052 | G130: 1.5719659 | H130: 80.887516 | I130: Enugu (325) | J130: Adamawa (200)
A131: Feb-2025 | B131: selected_food_table_Feb_25.xlsx | C131: Agric hen eggs, (a Crate of 30 pieces) | E131: 5878.1406 | F131: 5976.1159 | G131: 1.666772 | I131: Enugu (7250) | J131: Kogi (5000)
A132: Feb-2025 | B132: selected_food_table_Feb_25.xlsx | C132: Beans Brown | D132: 1177.9258 | E132: 2458.5333 | F132: 2465.9628 | G132: 0.30219169 | H132: 109.34789 | I132: Ebonyi (3200) | J132: Sokoto (1572.83)
A133: Feb-2025 | B133: selected_food_table_Feb_25.xlsx | C133: Beans white | D133: 1156.8221 | E133: 2123.853 | F133: 2114.3292 | G133: -0.44841891 | H133: 82.770467 | I133: Abia (2825.33) | J133: Yobe (1371.48)
A134: Feb-2025 | B134: selected_food_table_Feb_25.xlsx | C134: Beef Boneless | D134: 3654.5612 | E134: 6122.5683 | F134: 6269.4588 | G134: 2.3991652 | H134: 71.551615 | I134: Imo (8392.86) | J134: Benue (4250)
A135: Feb-2025 | B135: selected_food_table_Feb_25.xlsx | C135: Bread (sliced), 450g | E135: 1604.7842 | F135: 1633.1854 | G135: 1.7697791 | I135: Ogun (1950) | J135: Osun (1256.25)
A136: Feb-2025 | B136: selected_food_table_Feb_25.xlsx | C136: Bread (unsliced), 450g | E136: 1452.983 | F136: 1497.4272 | G136: 3.0588232 | I136: Akwa Ibom (1900) | J136: Yobe (900)
A137: Feb-2025 | B137: selected_food_table_Feb_25.xlsx | C137: Carrots, fresh | E137: 1787.1615 | F137: 1838.5928 | G137: 2.8778248 | I137: Imo (2557.14) | J137: Zamfara (1410)
A138: Feb-2025 | B138: selected_food_table_Feb_25.xlsx | C138: Cat fresh fish | D138: 2758.3787 | E138: 5226.8706 | F138: 5284.3595 | G138: 1.0998735 | H138: 91.574837 | I138: Plateau (7608.1) | J138: Kaduna (3500)
A139: Feb-2025 | B139: selected_food_table_Feb_25.xlsx | C139: Chicken feet | D139: 2313.4977 | E139: 3293.6296 | F139: 3346.6242 | G139: 1.6090049 | H139: 44.656477 | I139: Ondo (4750) | J139: Taraba (2100)
A140: Feb-2025 | B140: selected_food_table_Feb_25.xlsx | C140: Chicken meat (Frozen) | D140: 4370.7821 | E140: 5497.0311 | F140: 5552.7027 | G140: 1.012757 | H140: 27.041398 | I140: Enugu (8000) | J140: Sokoto (4200)
A141: Feb-2025 | B141: selected_food_table_Feb_25.xlsx | C141: Chicken Wings | D141: 2751.9042 | E141: 4340.1078 | F141: 4394.4054 | G141: 1.2510657 | H141: 59.685989 | I141: Niger (5598.22) | J141: Yobe (3009.25)
A142: Feb-2025 | B142: selected_food_table_Feb_25.xlsx | C142: Cray fish small white | E142: 6227.0407 | F142: 6440.4411 | G142: 3.4269948 | I142: Kogi (8000) | J142: Bayelsa (4300)
A143: Feb-2025 | B143: selected_food_table_Feb_25.xlsx | C143: Dried fish, Bonga | E143: 6131.9801 | F143: 6160.0213 | G143: 0.45729427 | I143: Enugu (9000) | J143: Adamawa (4000)
A144: Feb-2025 | B144: selected_food_table_Feb_25.xlsx | C144: Garri white | D144: 723.44894 | E144: 1267.6349 | F144: 1277.2471 | G144: 0.75827745 | H144: 76.549718 | I144: Kebbi (1693.78) | J144: Ogun (923.61)
A145: Feb-2025 | B145: selected_food_table_Feb_25.xlsx | C145: Garri Yellow | D145: 753.56405 | E145: 1358.9584 | F145: 1378.1547 | G145: 1.4125736 | H145: 82.88488 | I145: Kebbi (1744.39) | J145: Ekiti (961.54)
A146: Feb-2025 | B146: selected_food_table_Feb_25.xlsx | C146: Ginger, fresh | E146: 4206.7995 | F146: 4371.8969 | G146: 3.9245368 | I146: Rivers (5300) | J146: Katsina (2650)
A147: Feb-2025 | B147: selected_food_table_Feb_25.xlsx | C147: Goat Meat Bone in | E147: 6202.3575 | F147: 6298.8934 | G147: 1.5564387 | I147: Akwa Ibom (9500) | J147: Kogi (3800)
A148: Feb-2025 | B148: selected_food_table_Feb_25.xlsx | C148: Groundnut oil, 75cl | E148: 2939.7346 | F148: 3039.8295 | G148: 3.4048939 | I148: Ogun (3900) | J148: Abuja (2250)
A149: Feb-2025 | B149: selected_food_table_Feb_25.xlsx | C149: Groundnuts, roasted,75cl bottle | E149: 2387.7568 | F149: 2392.4711 | G149: 0.19743431 | I149: Bayelsa (3148.21) | J149: Osun (1900)
A150: Feb-2025 | B150: selected_food_table_Feb_25.xlsx | C150: Irish Potatoe | D150: 1130.6297 | E150: 1790.9109 | F150: 1756.4073 | G150: -1.9265956 | H150: 55.347702 | I150: Anambra (2782.21) | J150: Abuja (931.78)
A151: Feb-2025 | B151: selected_food_table_Feb_25.xlsx | C151: Local Rice (Broken) | E151: 2508.155 | F151: 2564.9518 | G151: 2.2644877 | I151: Ogun (4500) | J151: Yobe (1416.67)
A152: Feb-2025 | B152: selected_food_table_Feb_25.xlsx | C152: Mackerel, Frozen | D152: 2711.7728 | E152: 5117.8059 | F152: 5233.1514 | G152: 2.2538078 | H152: 92.978981 | I152: Plateau (8517.33) | J152: Oyo (3568.18)
A153: Feb-2025 | B153: selected_food_table_Feb_25.xlsx | C153: Maize (Corn) Grains (White) sold loose | D153: 729.45169 | E153: 1168.338 | F153: 1169.321 | G153: 0.084139931 | H153: 60.301365 | I153: Imo (1979.17) | J153: Yobe (687.5)
A154: Feb-2025 | B154: selected_food_table_Feb_25.xlsx | C154: Onions, fresh | D154: 915.60984 | E154: 1367.6216 | F154: 1372.0419 | G154: 0.32321366 | H154: 49.850061 | I154: Cross River (2483.33) | J154: Taraba (560)
A155: Feb-2025 | B155: selected_food_table_Feb_25.xlsx | C155: Palm oil, 75cl | D155: 1561.4594 | E155: 2329.5428 | F155: 2384.1511 | G155: 2.3441642 | H155: 52.687358 | I155: Ogun (3000) | J155: Adamawa (1500)
A156: Feb-2025 | B156: selected_food_table_Feb_25.xlsx | C156: Plantain (ripe) | D156: 846.5006 | E156: 1876.0259 | F156: 1914.499 | G156: 2.0507792 | H156: 126.16629 | I156: Abuja (2400) | J156: Gombe (1476.25)
A157: Feb-2025 | B157: selected_food_table_Feb_25.xlsx | C157: Plantain (unripe) | D157: 858.99191 | E157: 2119.0689 | F157: 2127.6713 | G157: 0.405949 | H157: 147.69398 | I157: Plateau (2886.64) | J157: Osun (1479.78)
A158: Feb-2025 | B158: selected_food_table_Feb_25.xlsx | C158: Rice Local, short-Grained | D158: 1222.9666 | E158: 2067.9978 | F158: 2088.8217 | G158: 1.0069575 | H158: 70.79957 | I158: Plateau (2600) | J158: Oyo (1516.13)
A159: Feb-2025 | B159: selected_food_table_Feb_25.xlsx | C159: Rice Long-Grained (Imported) | D159: 1549.4998 | E159: 2505.4794 | F159: 2565.0915 | G159: 2.3792674 | H159: 65.543193 | I159: Plateau (3190.91) | J159: Oyo (1938.71)
A160: Feb-2025 | B160: selected_food_table_Feb_25.xlsx | C160: Semovita, Prepacked (1kg) | E160: 2072.0012 | F160: 2089.7944 | G160: 0.85874402 | I160: Rivers (2580) | J160: Lagos (1800)
A161: Feb-2025 | B161: selected_food_table_Feb_25.xlsx | C161: Smoked fish (Mackerel) | E161: 5407.6327 | F161: 5458.019 | G161: 0.93176257 | I161: Kwara (8230) | J161: Kebbi (3401.7)
A162: Feb-2025 | B162: selected_food_table_Feb_25.xlsx | C162: Sweet potatoes | D162: 672.82863 | E162: 852.51531 | F162: 823.2987 | G162: -3.427107 | H162: 22.363804 | I162: Taraba (1594.31) | J162: Adamawa (520)
A163: Feb-2025 | B163: selected_food_table_Feb_25.xlsx | C163: Tilapia fresh fish (Epiya) | D163: 2445.2625 | E163: 5065.3632 | F163: 5103.942 | G163: 0.76162036 | H163: 108.72778 | I163: Benue (8239.29) | J163: Yobe (3750)
A164: Feb-2025 | B164: selected_food_table_Feb_25.xlsx | C164: Tin Milk-Evaporated, Peak Milk, 150g | D164: 635.99952 | E164: 928.00163 | F164: 931.03473 | G164: 0.32684271 | H164: 46.38922 | I164: Enugu (1200) | J164: Bayelsa (782.14)
A165: Feb-2025 | B165: selected_food_table_Feb_25.xlsx | C165: Tin Milk-Evaporated, Three Crown Milk, 160g | E165: 837.23255 | F165: 827.31484 | G165: -1.1845821 | I165: Bayelsa (1057.14) | J165: Kogi (650)
A166: Feb-2025 | B166: selected_food_table_Feb_25.xlsx | C166: Titus, frozen | D166: 2883.0738 | E166: 5467.2313 | F166: 5564.2891 | G166: 1.7752629 | H166: 92.998497 | I166: Kwara (8343.26) | J166: Yobe (4200)
A167: Feb-2025 | B167: selected_food_table_Feb_25.xlsx | C167: Tomatoes, fresh | D167: 937.84841 | E167: 1081.4391 | F167: 1111.1396 | G167: 2.7463822 | H167: 18.477526 | I167: Ebonyi (1787.31) | J167: Kebbi (624.32)
A168: Feb-2025 | B168: selected_food_table_Feb_25.xlsx | C168: Vegetable Oil, 75cl | D168: 1878.8123 | E168: 2975.9619 | F168: 3090.5104 | G168: 3.8491239 | H168: 64.49277 | I168: Ekiti (4648.67) | J168: Adamawa (2200)
A169: Feb-2025 | B169: selected_food_table_Feb_25.xlsx | C169: Watermelon whole, medium size fresh | E169: 1850.8433 | F169: 1926.2041 | G169: 4.0717035 | I169: Anambra (2795) | J169: Zamfara (1100)
A170: Feb-2025 | B170: selected_food_table_Feb_25.xlsx | C170: Wheat Flour, Prepacked (2kg) | D170: 2277.5858 | E170: 3847.3657 | F170: 3890.803 | G170: 1.1290142 | H170: 70.830139 | I170: Imo (5616.67) | J170: Bauchi (2800)
A171: Feb-2025 | B171: selected_food_table_Feb_25.xlsx | C171: Yam Tuber | D171: 1009.556 | E171: 1991.3299 | F171: 2022.0329 | G171: 1.5418325 | H171: 100.28933 | I171: Imo (2535.03) | J171: Ondo (1417.87)
A172: Mar-2025 | B172: selected_food_table_Mar_25.xlsx | C172: Agric hen eggs, | D172: 147.92334 | E172: 251.94052 | F172: 261.18235 | G172: 3.6682586 | H172: 76.566018 | I172: Enugu (354.75) | J172: Kaduna (210)
A173: Mar-2025 | B173: selected_food_table_Mar_25.xlsx | C173: Agric hen eggs, (a Crate of 30 pieces) | E173: 5976.1159 | F173: 7670.5592 | G173: 28.353589 | I173: Enugu (7930) | J173: Niger (5300)
A174: Mar-2025 | B174: selected_food_table_Mar_25.xlsx | C174: Beans Brown | D174: 1234.4022 | E174: 2465.9628 | F174: 2616.2636 | G174: 6.0950166 | H174: 111.9458 | I174: Abia (3651.13) | J174: Sokoto (1634.36)
...
